Workbook

Sheet Caregiver Pipeline
A1: Tuniti Care Hero – Caregiver Training Pipeline
A3: # | B3: Caregiver Name | C3: Intake | D3: Course Start | E3: Available From | F3: Avg Score | G3: Practical Status | H3: Qualified | I3: Matched Name (Billing) | J3: Total Billed (ZAR)
A4: 1 | B4: Akhona Nomonde Mkize | C4: Tranche 1 | D4: 45918 | E4: 45981 | F4: 0.9257 | G4: Completed | H4: Completed 288 Hours | I4: — | J4: 0
A5: 2 | B5: Elly Dhlabo | C5: Tranche 1 | D5: 45918 | E5: 45981 | F5: 0.8486 | G5: Completed | H5: Completed 288 Hours | I5: — | J5: 0
A6: 3 | B6: Jolie Mpunga | C6: Tranche 1 | D6: 45918 | E6: 45981 | F6: 0.63 | G6: Completed | H6: Completed 288 Hours | I6: — | J6: 0
A7: 4 | B7: Jovani Mukuna Tshibingu | C7: Tranche 1 | D7: 45918 | E7: 45981 | F7: 0.96 | G7: Completed | H7: Completed 288 Hours | I7: — | J7: 0
A8: 5 | B8: Mafusi Elizabeth Mofokeng | C8: Tranche 1 | D8: 45918 | E8: 45981 | F8: 0.8571 | G8: Completed | H8: Completed 288 Hours | I8: — | J8: 0
A9: 6 | B9: Minenhle Nkazimulo Fuyane | C9: Tranche 1 | D9: 45918 | E9: 45981 | F9: 0.8571 | G9: Completed | H9: Completed 288 Hours | I9: — | J9: 0
A10: 7 | B10: Miriam Mehlomakulu | C10: Tranche 1 | D10: 45918 | E10: 45981 | F10: 0.5367 | G10: Completed | H10: Completed 288 Hours | I10: — | J10: 0
A11: 8 | B11: Mukuna Mbuyi | C11: Tranche 1 | D11: 45918 | E11: 45981 | F11: 0.6314 | G11: Completed | H11: Completed 288 Hours | I11: — | J11: 0
A12: 9 | B12: Nelly | C12: Tranche 1 | D12: 45918 | E12: 45981 | F12: 0.76 | G12: Relocated | H12: No | I12: — | J12: 0
A13: 10 | B13: Ramogohlo Daphney Aphane | C13: Tranche 1 | D13: 45918 | E13: 45981 | F13: 0.7171 | G13: Completed | H13: Completed 288 Hours | I13: — | J13: 0
A14: 11 | B14: Siphiwe Nelly Ezeadum | C14: Tranche 1 | D14: 45918 | E14: 45981 | F14: 0.5017 | G14: Completed | H14: Completed 288 Hours | I14: — | J14: 0
A15: 12 | B15: Sylvie Lubamba Mbaya | C15: Tranche 1 | D15: 45918 | E15: 45981 | F15: 0.84 | G15: Completed | H15: Completed 288 Hours | I15: — | J15: 0
... A85: 82 | B85: Pusheletso Mashego Mashabela | C85: Tranche 6 | D85: 46035 | E85: 46098 | F85: 0.6273 | G85: Still busy | H85: No | I85: — | J85: 0
A86: 83 | B86: Queen Ramokone Sibanda | C86: Tranche 6 | D86: 46035 | E86: 46098 | G86: Not started | H86: No | I86: — | J86: 0
A87: 84 | B87: Rita Ncube | C87: Tranche 6 | D87: 46035 | E87: 46098 | F87: 0.7689 | G87: Still busy | H87: No | I87: — | J87: 0
A88: 85 | B88: Violet Labvu | C88: Tranche 6 | D88: 46035 | E88: 46098 | F88: 0.9025 | G88: Still busy | H88: No | I88: — | J88: 0
A89: 86 | B89: Bekithemba Mpofu | C89: Tranche 7 | D89: 46036 | E89: 46099 | F89: 0.789 | G89: Not started | H89: No | I89: — | J89: 0
A90: 87 | B90: Blessing Rofhiwa Ndou | C90: Tranche 7 | D90: 46036 | E90: 46099 | F90: 0.5517 | G90: Not started | H90: No | I90: — | J90: 0
A91: 88 | B91: Immaculate Tshegofatso Mataboge | C91: Tranche 7 | D91: 46036 | E91: 46099 | F91: 0.8267 | G91: Not started | H91: No | I91: — | J91: 0
A92: 89 | B92: Josephine Olaide Olaleye | C92: Tranche 7 | D92: 46036 | E92: 46099 | F92: 0.6933 | G92: Not started | H92: No | I92: — | J92: 0
A93: 90 | B93: Lydia James Banda | C93: Tranche 7 | D93: 46036 | E93: 46099 | F93: 0.918 | G93: Not started | H93: No | I93: — | J93: 0
A94: 91 | B94: Margaret Mamatime Dimakatso Aphane | C94: Tranche 7 | D94: 46036 | E94: 46099 | F94: 0.745 | G94: Still busy | H94: No | I94: — | J94: 0
A95: 92 | B95: Mary Komwedzai | C95: Tranche 7 | D95: 46036 | E95: 46099 | F95: 0.5892 | G95: Still busy | H95: No | I95: — | J95: 0
A96: 93 | B96: Octovia Xitsundzuxo Marhanele | C96: Tranche 7 | D96: 46036 | E96: 46099 | F96: 0.861 | G96: Not started | H96: No | I96: — | J96: 0
A97: 94 | B97: Patience Sesi Poto | C97: Tranche 7 | D97: 46036 | E97: 46099 | F97: 0.724 | G97: Still busy | H97: No | I97: — | J97: 0
A98: 95 | B98: Sandra Mhaka | C98: Tranche 7 | D98: 46036 | E98: 46099 | F98: 0.6325 | G98: Still busy | H98: No | I98: — | J98: 0
... A113: 110 | B113: Xolile Fortunate Mabizela | C113: Tranche 8 | D113: 46037 | E113: 46100 | F113: 0.6428 | G113: Not started | H113: No | I113: — | J113: 0
A114: 111 | B114: Juliet Tshakane Lekgothoane | C114: Tranche 9 | D114: 46038 | E114: 46108 | G114: Not started | H114: Pending | I114: — | J114: 0
A115: 112 | B115: Karabo Mabye | C115: Tranche 9 | D115: 46038 | E115: 46108 | G115: Not started | H115: Pending | I115: — | J115: 0
A116: 113 | B116: Leandra Sharlen Emalize Williams | C116: Tranche 9 | D116: 46038 | E116: 46108 | G116: Not started | H116: Pending | I116: — | J116: 0
A117: 114 | B117: Lisa Thembi Phasha | C117: Tranche 9 | D117: 46038 | E117: 46108 | G117: Not started | H117: Pending | I117: — | J117: 0
A118: 115 | B118: Mamohlolo Nkalai | C118: Tranche 9 | D118: 46038 | E118: 46108 | G118: Not started | H118: Pending | I118: — | J118: 0
A119: 116 | B119: Marlise Louise Els | C119: Tranche 9 | D119: 46038 | E119: 46108 | G119: Not started | H119: Pending | I119: — | J119: 0
A120: 117 | B120: Mashudu Thalitha Managa | C120: Tranche 9 | D120: 46038 | E120: 46108 | G120: Not started | H120: Pending | I120: — | J120: 0
A121: 118 | B121: Philadelpia Tsakani Mashaba | C121: Tranche 9 | D121: 46038 | E121: 46108 | G121: Not started | H121: Pending | I121: — | J121: 0
A122: 119 | B122: Prisca Ndlovu | C122: Tranche 9 | D122: 46038 | E122: 46108 | G122: Not started | H122: Pending | I122: — | J122: 0
A123: 120 | B123: Reshoketswe Amber Makgahlela | C123: Tranche 9 | D123: 46038 | E123: 46108 | G123: Not started | H123: Pending | I123: — | J123: 0
A124: 121 | B124: Sinqobile Chiropa | C124: Tranche 9 | D124: 46038 | E124: 46108 | G124: Not started | H124: Pending | I124: Thalitha Managa | J124: 2000
A125: 122 | B125: Siphesihle Rabotho | C125: Tranche 9 | D125: 46038 | E125: 46108 | G125: Not started | H125: Pending | I125: Philadelphia Mashaba | J125: 3000
A126: 123 | B126: Victoria Mandlovu Mkhonza | C126: Tranche 9 | D126: 46038 | E126: 46108 | G126: Not started | H126: Pending | I126: — | J126: 0
A128: UNMATCHED — Caregivers billing through TCH but not in Tuniti training pipeline
A129: # | B129: Caregiver Name | C129: Tranche | D129: Course Start | E129: Available From | F129: Avg Score | G129: Practical Status | H129: Qualified | I129: Matched Name (Billing) | J129: Total Billed (ZAR)
A130: 124 | B130: Adaobi Ejikeme | C130: Tranche N/K | D130: N/A | E130: N/A | F130: N/A | G130: N/A | H130: N/A | I130: Adaobi Ejikeme | J130: 30600
A131: 125 | B131: Annika Van Rensburg | C131: Tranche N/K | D131: N/A | E131: N/A | F131: N/A | G131: N/A | H131: N/A | I131: Annika Van Rensburg | J131: 9170
A132: 126 | B132: Christina Maluleka | C132: Tranche N/K | D132: N/A | E132: N/A | F132: N/A | G132: N/A | H132: N/A | I132: Christina Maluleka | J132: 49050
A133: 127 | B133: Cynthia Makondo | C133: Tranche N/K | D133: N/A | E133: N/A | F133: N/A | G133: N/A | H133: N/A | I133: Cynthia Makondo | J133: 30800
A134: 128 | B134: Dolly Chauke | C134: Tranche N/K | D134: N/A | E134: N/A | F134: N/A | G134: N/A | H134: N/A | I134: Dolly Chauke | J134: 3000
A135: 129 | B135: Emiia Mshaba | C135: Tranche N/K | D135: N/A | E135: N/A | F135: N/A | G135: N/A | H135: N/A | I135: Emiia Mshaba | J135: 9850
A136: 130 | B136: Emily Mentula | C136: Tranche N/K | D136: N/A | E136: N/A | F136: N/A | G136: N/A | H136: N/A | I136: Emily Mentula | J136: 38060
A137: 131 | B137: Joyce Mutambiranwa | C137: Tranche N/K | D137: N/A | E137: N/A | F137: N/A | G137: N/A | H137: N/A | I137: Joyce Mutambiranwa | J137: 36800
A138: 132 | B138: Linda Rapuluchukwa | C138: Tranche N/K | D138: N/A | E138: N/A | F138: N/A | G138: N/A | H138: N/A | I138: Linda Rapuluchukwa | J138: 50700
A139: 133 | B139: Martha Mashishi | C139: Tranche N/K | D139: N/A | E139: N/A | F139: N/A | G139: N/A | H139: N/A | I139: Martha Mashishi | J139: 450
A140: 134 | B140: Mbali Ndaba | C140: Tranche N/K | D140: N/A | E140: N/A | F140: N/A | G140: N/A | H140: N/A | I140: Mbali Ndaba | J140: 7150
A141: 135 | B141: Monique Bosch | C141: Tranche N/K | D141: N/A | E141: N/A | F141: N/A | G141: N/A | H141: N/A | I141: Monique Bosch | J141: 2547
... A146: 140 | B146: Sylvia Nene | C146: Tranche N/K | D146: N/A | E146: N/A | F146: N/A | G146: N/A | H146: N/A | I146: Sylvia Nene | J146: 26535
A149: SUMMARY
B150: Tuniti-trained caregivers (Tranches 1–9) | D150: 123
B151: — Fully qualified (288 hrs completed) | D151: 39
B152: — Practicals still busy | D152: 25
B153: — Practicals not started | D153: 38
B154: Tuniti-trained actively billing through TCH | D154: 25
B155: — Total billed by matched caregivers | D155: R 319,458
B157: Non-Tuniti caregivers billing (Tranche N/K) | D157: 17
B158: — Total billed by non-Tuniti caregivers | D158: R 390,162
B160: Total caregivers in system | D160: 140
B161: Total billed (all caregivers) | D161: R 709,620

Sheet Client Summary
A1: TCH Holdings – Client Income Summary (ZAR)
A3: Client | B3: Nov 2025 | C3: Dec 2025 | D3: Jan 2026 | E3: Feb 2026 | F3: Mar 2026 | G3: Apr 2026 | H3: Total
A4: Johnstons | B4: 24000 | C4: 24800 | D4: 23250 | E4: 21000 | F4: 24800 | G4: 16500 | H4: =SUM(B4:G4)
A5: Van Der Linde | B5: 22200 | C5: 22200 | D5: 22200 | E5: 22200 | F5: 22200 | G5: 0 | H5: =SUM(B5:G5)
A6: Hennie | B6: 18600 | C6: 4650 | D6: 0 | E6: 0 | F6: 0 | G6: 0 | H6: =SUM(B6:G6)
A7: John Bierman | B7: 16000 | C7: 18400 | D7: 17600 | E7: 16000 | F7: 17000 | G7: 17600 | H7: =SUM(B7:G7)
A8: Hillery | B8: 3800 | C8: 2850 | D8: 0 | E8: 0 | F8: 0 | G8: 0 | H8: =SUM(B8:G8)
A9: Van Vuuren | B9: 23200 | C9: 0 | D9: 0 | E9: 0 | F9: 0 | G9: 0 | H9: =SUM(B9:G9)
A10: Trevor Botes | B10: 15000 | C10: 16500 | D10: 14250 | E10: 13500 | F10: 17250 | G10: 16500 | H10: =SUM(B10:G10)
A11: Johann Roos | B11: 14000 | C11: 11900 | D11: 0 | E11: 0 | F11: 0 | G11: 0 | H11: =SUM(B11:G11)
A12: Ishaan/Elizabth | B12: 13300 | C12: 0 | D12: 0 | E12: 0 | F12: 0 | G12: 0 | H12: =SUM(B12:G12)
A13: Androilla/ Praxia | B13: 21000 | C13: 7500 | D13: 0 | E13: 0 | F13: 0 | G13: 0 | H13: =SUM(B13:G13)
A14: Jacomina/Charl | B14: 3800 | C14: 0 | D14: 0 | E14: 0 | F14: 0 | G14: 0 | H14: =SUM(B14:G14)
A15: Herman/Rene | B15: 4250 | C15: 0 | D15: 0 | E15: 0 | F15: 0 | G15: 0 | H15: =SUM(B15:G15)
... A56: Anton Steyn/ Emce | B56: 0 | C56: 0 | D56: 0 | E56: 0 | F56: 0 | G56: 3800 | H56: =SUM(B56:G56)
A57: TOTAL | B57: =SUM(B4:B56) | C57: =SUM(C4:C56) | D57: =SUM(D4:D56) | E57: =SUM(E4:E56) | F57: =SUM(F4:F56) | G57: =SUM(G4:G56) | H57: =SUM(H4:H56)
A58: Sheet Total (validation) | B58: 201150 | C58: 223287 | D58: 242994 | E58: 274922 | F58: 370000 | G58: 261200

Sheet Caregiver Summary
A1: TCH Holdings – Caregiver Pay Summary (ZAR)
A3: Caregiver | B3: Nov 2025 | C3: Dec 2025 | D3: Jan 2026 | E3: Feb 2026 | F3: Mar 2026 | G3: Apr 2026 | H3: Total
A4: Linda Rapuluchukwa | B4: 9600 | C4: 9600 | D4: 9600 | E4: 11400 | F4: 10500 | G4: 0 | H4: =SUM(B4:G4)
A5: Sophie Koga | B5: 11250 | C5: 9450 | D5: 10800 | E5: 7450 | F5: 1650 | G5: 0 | H5: =SUM(B5:G5)
A6: Joyce Mutambiranwa | B6: 3150 | C6: 6750 | D6: 10000 | E6: 8900 | F6: 8000 | G6: 0 | H6: =SUM(B6:G6)
A7: Emily Mentula | B7: 3600 | C7: 9450 | D7: 8360 | E7: 7200 | F7: 9450 | G7: 0 | H7: =SUM(B7:G7)
A8: Cynthia Makondo | B8: 8750 | C8: 4200 | D8: 3050 | E8: 7150 | F8: 7650 | G8: 0 | H8: =SUM(B8:G8)
A9: Ruth Nnadi | B9: 0 | C9: 6750 | D9: 7200 | E9: 4950 | F9: 7100 | G9: 0 | H9: =SUM(B9:G9)
A10: Christina Maluleka | B10: 9000 | C10: 9450 | D10: 9450 | E10: 9000 | F10: 12150 | G10: 0 | H10: =SUM(B10:G10)
A11: Mzee Mzwakhe | B11: 6450 | C11: 9400 | D11: 0 | E11: 0 | F11: 0 | G11: 0 | H11: =SUM(B11:G11)
A12: Susan Murire | B12: 5850 | C12: 0 | D12: 7425 | E12: 9000 | F12: 9900 | G12: 0 | H12: =SUM(B12:G12)
A13: Ndai Mapenyenye | B13: 0 | C13: 0 | D13: 0 | E13: 3150 | F13: 8000 | G13: 0 | H13: =SUM(B13:G13)
A14: Adaobi Ejikeme | B14: 6300 | C14: 6750 | D14: 3600 | E14: 6650 | F14: 7300 | G14: 0 | H14: =SUM(B14:G14)
A15: Merriam Maluleke | B15: 4500 | C15: 3340 | D15: 4924 | E15: 2700 | F15: 8000 | G15: 0 | H15: =SUM(B15:G15)
... A45: Annie Mabuto | B45: 0 | C45: 0 | D45: 0 | E45: 0 | F45: 2650 | G45: 0 | H45: =SUM(B45:G45)
A46: TOTAL | B46: =SUM(B4:B45) | C46: =SUM(C4:C45) | D46: =SUM(D4:D45) | E46: =SUM(E4:E45) | F46: =SUM(F4:F45) | G46: =SUM(G4:G45) | H46: =SUM(H4:H45)

Sheet Margin Summary
A1: TCH Holdings – Gross Margin Summary (ZAR)
A3: CONSOLIDATED P&L
B5: Nov 2025 | C5: Dec 2025 | D5: Jan 2026 | E5: Feb 2026 | F5: Mar 2026 | G5: Apr 2026 | H5: Total
A6: Total Client Revenue | B6: ='Client Summary'!B57 | C6: ='Client Summary'!C57 | D6: ='Client Summary'!D57 | E6: ='Client Summary'!E57 | F6: ='Client Summary'!F57 | G6: ='Client Summary'!G57 | H6: ='Client Summary'!H57
A7: Total Caregiver Cost | B7: ='Caregiver Summary'!B46 | C7: ='Caregiver Summary'!C46 | D7: ='Caregiver Summary'!D46 | E7: ='Caregiver Summary'!E46 | F7: ='Caregiver Summary'!F46 | G7: ='Caregiver Summary'!G46 | H7: ='Caregiver Summary'!H46
A8: Gross Margin | B8: =B6-B7 | C8: =C6-C7 | D8: =D6-D7 | E8: =E6-E7 | F8: =F6-F7 | G8: =G6-G7 | H8: =H6-H7
A9: Gross Margin % | B9: =IF(B6=0,0,B8/B6) | C9: =IF(C6=0,0,C8/C6) | D9: =IF(D6=0,0,D8/D6) | E9: =IF(E6=0,0,E8/E6) | F9: =IF(F6=0,0,F8/F6) | G9: =IF(G6=0,0,G8/G6) | H9: =IF(H6=0,0,H8/H6)
A11: Note: Apr 2026 caregiver sheet is empty — margin for Apr reflects revenue only.
A13: PER-CLIENT MARGIN (Nov–Dec 2025, where expense data available)
A15: Client | B15: Income | C15: Expense | D15: Margin | E15: Margin % | F15: Month | G15: Source Sheet
A16: Johnstons | B16: 24000 | C16: 19400 | D16: 4600 | E16: 0.19166667 | F16: Nov 2025 | G16: Clients Nov 2025
A17: Van Der Linde | B17: 22200 | C17: 14441 | D17: 7759 | E17: 0.3495045 | F17: Nov 2025 | G17: Clients Nov 2025
A18: Hennie | B18: 18600 | C18: 13471 | D18: 5129 | E18: 0.27575269 | F18: Nov 2025 | G18: Clients Nov 2025
A19: John Bierman | B19: 16000 | C19: 6450 | D19: 9550 | E19: 0.596875 | F19: Nov 2025 | G19: Clients Nov 2025
A20: Hillery | B20: 3800 | C20: 2250 | D20: 1550 | E20: 0.40789474 | F20: Nov 2025 | G20: Clients Nov 2025
A21: Van Vuuren | B21: 23200 | C21: 10800 | D21: 12400 | E21: 0.53448276 | F21: Nov 2025 | G21: Clients Nov 2025
A22: Trevor Botes | B22: 15000 | C22: 8450 | D22: 6550 | E22: 0.43666667 | F22: Nov 2025 | G22: Clients Nov 2025
A23: Johann Roos | B23: 14000 | C23: 7000 | D23: 7000 | E23: 0.5 | F23: Nov 2025 | G23: Clients Nov 2025
A24: Ishaan/Elizabth | B24: 13300 | C24: 6300 | D24: 7000 | E24: 0.52631579 | F24: Nov 2025 | G24: Clients Nov 2025
A25: Androilla/ Praxia | B25: 21000 | C25: 11250 | D25: 9750 | E25: 0.46428571 | F25: Nov 2025 | G25: Clients Nov 2025
A26: Jacomina/Charl | B26: 3800 | C26: 9900 | D26: -6100 | E26: -1.6052632 | F26: Nov 2025 | G26: Clients Nov 2025
A27: Herman/Rene | B27: 4250 | C27: 2250 | D27: 2000 | E27: 0.47058824 | F27: Nov 2025 | G27: Clients Nov 2025
... A55: Scroope | B55: 3350 | C55: 0 | D55: 3350 | E55: 1 | F55: Apr 2026 | G55: Client Apr 2026

Sheet Caregiver Banking Details 
A1: Caregiver name | B1: Bank Name | C1: Account Number | D1: Account Type
A2: Linda Rapuluchukwa | B2: Capitec | C2: 1341317429 | D2: Savings | E2: Daily Rate
A3: Sophie Koga | B3: Bidvest Bank | C3: 78604588265 | D3: Current | E3: Daily Rate
A4: Joyce Mutambiranwa | B4: FNB | C4: 62785415649 | D4: Current | E4: Daily Rate
A5: Emily Mentula | B5: Capitec | C5: 1433103425 | D5: Savings | E5: Daily Rate
A6: Cynthia Makondo | B6: Capitec | C6: 1399500110 | D6: Savings | E6: Daily Rate
A7: Ruth Nnadi | B7: FNB | C7: 63124004473 | D7: Savings | E7: Daily Rate
A8: Christina Maluleka | B8: Standard Bank | C8: 10078950056 | D8: Current | E8: Daily Rate
A9: Mzee Mzwakhe | B9: FNB | C9: 63165744468 | D9: Current | E9: Daily Rate
A10: Susan Murire | B10: Capitec | C10: 1499687921 | D10: Savings | E10: Daily Rate
A11: Ndai Mapenyenye | B11: FNB | C11: 62353233168 | D11: Current | E11: Daily Rate
A12: Adaobi Ejikeme | B12: Standard Bank | C12: 10225922116 | D12: Current | E12: Daily Rate
A13: Merriam Maluleke | B13: Tyme Bank | C13: 51022803799 | D13: Savings | E13: Daily Rate
... A25: Matshidiso Leah Aphane | B25: Standard Bank | C25: 10198039598 | D25: Savings | E25: Set Rate- R7000
A26: Monique Bosch | B26: ABSA | C26: 9346827597 | D26: Current
A27: Nhlakanipho (Nipho) Tshabalala | B27: Capitec | C27: 1657265011 | D27: Savings | E27: Daily Rate
A28: Musa Zulu | B28: Standard Bank | C28: 10220227606 | D28: Current | E28: Daily Rate
A29: Busisiwe Mandiyanike | B29: Capitec | C29: 1824878654 | D29: Savings | E29: Daily Rate
A30: Julia Ramoroka | B30: Capitec | C30: 1699069881 | D30: Savings | E30: Daily Rate
A31: Martha Mashishi | B31: FNB | C31: 63184912434 | D31: Current | E31: Daily Rate
A32: Emilia Masvosva | B32: FNB | C32: 63187909420 | D32: Savings | E32: Daily Rate
A33: Sara Mdaka | B33: Standard Bank | C33: 10178989965 | D33: Savings | E33: Daily Rate
A34: Martha Sona | B34: Standard Bank | C34: 10155598854 | D34: Savings | E34: Daily Rate
A35: Mbali Ndaba | B35: Capitec | C35: 1498440809 | D35: Savings | E35: Daily Rate
A36: Philadelphia Mashaba | B36: Capitec | C36: 1664129756 | D36: Savings | E36: Daily Rate
A37: Annika Van Rensburg | B37: ABSA | C37: 9371060605 | D37: Savings | E37: 9600
A38: Fortunate Mabizela | B38: Capitec | C38: 1474680087 | D38: Savings | E38: Daily Rate
A39: Beauty Masopye | B39: Capitec | C39: 1289579669 | D39: Savings | E39: Daily Rate
A40: Thalitha Managa | B40: Capitec | C40: 1372172848 | D40: Savings | E40: Daily Rate
A41: Dolly Chauke | B41: Standard Bank | C41: 10140799891 | D41: Savings | E41: Daily Rate
A42: Annie Mabuto | B42: FNB | C42: 62417698836 | D42: Savings | E42: Daily Rate

Sheet Clients
A1: Patient Name | B1: Client Name | C1: Day Rate | D1: Monthly/ Weekly | E1: Day Shift/ Live In | F1: Full Time/ | G1: NPC/TCH | H1: Total Amount | I1: Active/ Not Active
A2: Pat Johnston | B2: Johnston | C2: 750 | D2: Monthly | E2: Live-In | F2: Mon- Fri | G2: NPC | I2: Active
A3: Tannie Annetjie | B3: Marisáne Gerber | C3: N/A | D3: Monthly | E3: Live-In | F3: Full Time | G3: NPC | H3: 22200 | I3: Not Active
A4: Bierman | B4: Dr Heleen Bieman Inc | C4: 800 | D4: Monthly | E4: Day Shift | F4: Mon- Fri | G4: TCH | I4: Active
A5: Boets | B5: M Boets | C5: 750 | D5: Monthly | E5: Day Shift | F5: Mon- Fri | G5: TCH | I5: Active
A6: Roos | B6: Andries Van der Merwe | C6: 700 | D6: Monthly | E6: Day Shift | F6: Mon- Fri | G6: TCH | I6: Not Active
A7: Le Roux | B7: Dr DA Le Roux Inc | C7: 750 | D7: Monthly | E7: Day Shift | F7: Every Thursday | G7: TCH | I7: Active
A8: Ras | B8: Marinus Ras | C8: 850 | D8: Monthly | E8: Live-In | F8: 14 Days Per Month | G8: TCH | H8: 11900 | I8: Active
A9: Tannie Klientjie | B9: Brenda Havenga | C9: N/A | D9: Monthly | E9: Live-In | F9: Full Time | G9: TCH | H9: 23250 | I9: Active
A10: Theron | B10: Quintus Theron | C10: 750 | D10: Monthly | E10: Day Shift | F10: Mon- Fri | G10: TCH | I10: Not Active
A11: Du Plessis | B11: Mathilnda Louisa Du Plessis | C11: N/A | D11: Monthly | E11: Day Shift | F11: Mon- Fri | G11: TCH | H11: 12500 | I11: Active
A12: Barnes | B12: Megan Louise Barnes | C12: N/A | D12: Monthly | E12: Day Shift | F12: 20 days per month | G12: TCH | H12: 13000 | I12: Active
A13: Sui Fon | B13: Julian Sam | C13: 678.57 | D13: Weekly | E13: Day Shift | F13: Discuss Weekly | G13: TCH | I13: Not Active
A14: Papau | B14: Angela Emily Piper | C14: 950 | D14: Weekly | E14: Live-In | F14: Full Time | G14: TCH | H14: 6650 | I14: Active
A15: Wessels | B15: Veron Wessels | C15: 1050 | D15: Monthly | E15: Day Shift | F15: Every Wednesday | G15: TCH | I15: Not Active
A16: Lotz | B16: Rene Lotz | C16: 800 | D16: Weekly | E16: Day Shift | F16: Mon- Fri | G16: TCH | I16: Not Active
A17: Scroope | B17: Jonathan Scroope | C17: 2500 | D17: As and when | E17: Live-In | F17: Fri-Mon | G17: TCH | I17: Active
A18: Diane Blumenthal | B18: Darren Blumenthal | C18: 900 | D18: As and when | E18: Night Shift | F18: 3 days | G18: TCH | I18: Not Active
A19: Cecily Hall | B19: Derke Hall | C19: 750 | D19: Monthly | E19: Day Shift | F19: Mon- Fri | G19: TCH | I19: Active
A20: Morrison | B20: Sandra Nell Morrison | C20: 750 | D20: Weekly | E20: Day Shift | F20: Mon- Fri | G20: TCH | I20: Not Active
A21: Anne Botha | B21: Berthe Botha | C21: 750 | D21: As and when | E21: Day Shift | G21: TCH | I21: Not Active
A22: Scholtz | B22: Dr CPT Scholtz | C22: 750 | E22: Day Shift | F22: Mon & Thur | G22: TCH | I22: Active
A23: Maria | B23: Yvonne Anne Burgum | C23: 750 | D23: Weekly | E23: Day Shift | F23: Mon, Wed, Fri | G23: TCH | I23: Active
A24: Ruth Place | B24: Dr Jean Meredith Place | C24: 800 | D24: As and when | E24: Day Shift | G24: TCH | I24: Active
A25: Roux | B25: Esme Kluckow | C25: 750 | D25: Monthly | E25: Day Shift | F25: Mon- Wed & Fri | G25: TCH | I25: Passed Away
A26: Carolina Richards | B26: Dawn Vivian Boyer de la Giroday | C26: 750 | D26: Monthly | E26: Day Shift | F26: Mon- Sun | G26: TCH | I26: Active
A27: Webb | B27: Sonja Sarantis | C27: 750 | D27: Weekly | E27: Day Shift | F27: Every Friday | G27: TCH | I27: Active
A28: Hardy | C28: 750
A29: Oosthuizen | B29: Hendrik Petrus Oosthuizen | C29: 750 | D29: Weekly | E29: Day Shift | F29: Mon- Fri | G29: TCH | I29: Active
A30: O'Neill | B30: Micheal O'Niel | C30: 850 | D30: Monthly | E30: Day Shift | F30: Mon-Sun | G30: TCH | I30: Active
A31: De Waal | B31: Erena Janse van Rensburg | C31: 950 | D31: Weekly | E31: Live-In | F31: Mon-Sun | G31: TCH | I31: Active
A32: Fisher | B32: Lynn Fisher | C32: N/A | D32: Monthly | E32: 2 Days per month | G32: TCH | H32: 5500 | I32: Active
A33: Nicolaas Alberts | B33: Nicolaas Alberts | C33: 950 | D33: As and when | G33: TCH
A34: Carli Peens | B34: Hendrik Peens | C34: 1500 | D34: Weekly | E34: 24 Hours | F34: Mon- Sun | G34: TCH | I34: Active
A35: Ingham | B35: Kenneth Ingham | C35: Night - R950 Day- R800 | D35: Daily | E35: 24 Hours | F35: Mon- Sun | G35: TCH | I35: Active
A36: Anna-Marie | B36: Helene Griffiths | C36: Live in - R950 | D36: As and when | E36: Live-In | G36: TCH | I36: Active
A37: Emce Bruinette | B37: Anton Styen | C37: Live in - R950 | D37: As and when | G37: TCH | I37: Active

Sheet Clients Nov 2025
A1: Johnstons | E1: Van Der Linde | I1: Hennie | M1: John Bierman | Q1: Hillery
A2: Income | E2: Income | I2: Income | M2: Income | Q2: Income
A3: Date: | C3: Payment | E3: Date: | G3: Payment | I3: Date: | K3: Payment | M3: Date: | O3: Payment | Q3: Date: | S3: Payment
A4: 45962 | C4: 24000 | E4: 45962 | G4: 22200 | I4: 45962 | K4: 4650 | M4: 45962 | O4: 16000 | Q4: 45962 | S4: 1900
I5: 45971 | K5: 4650 | Q5: 45990 | S5: 1900
I6: 45978 | K6: 4650
I7: 45985 | K7: 4650
C8: =SUM(C4:C7) | G8: =SUM(G4:G7) | K8: =SUM(K4:K7) | O8: =SUM(O4:O7) | S8: =SUM(S4:S7)
A9: Expenses | E9: Expenses | I9: Expenses | M9: Expenses | Q9: Expenses
A10: Date: | B10: Expense Name | C10: Amount | E10: Date: | F10: Expense Name | G10: Amount | I10: Date: | J10: Expense Name | K10: Amount | M10: Date: | N10: Expense Name | O10: Amount | Q10: Date: | R10: Expense Name | S10: Amount
A11: 45962 | B11: Linda | C11: 9600 | E11: 45962 | F11: Emily | G11: 3600 | I11: 45962 | J11: Cynthia | K11: 8750 | M11: 45962 | N11: Mzee | O11: 6450 | Q11: 45962 | R11: Tracy | S11: 2250
A12: 45962 | B12: Ada | C12: 6300 | E12: 45962 | F12: Joyce | G12: 900 | I12: 45962 | J12: Uber | K12: 4721
A13: 45962 | B13: Ada Stipens | C13: 3500 | E13: 45962 | F13: Emma | G13: 9000
E14: 45962 | F14: Uber | G14: 941
A23: Total Expense | C23: =SUM(C11:C22) | E23: Total Expense | G23: =SUM(G11:G22) | I23: Total Expense | K23: =SUM(K11:K22) | M23: Total Expense | O23: =SUM(O11:O22) | Q23: Total Expense | S23: =SUM(S11:S22)
A24: Income - Expense | C24: =MIN(C4-C23) | E24: Income - Expense | G24: =MIN(G4-G23) | I24: Income - Expense | K24: =MIN(K8-K23) | M24: Income - Expense | O24: =MIN(O4-O23) | Q24: Income - Expense | S24: =MIN(S8-S23)
A26: Van Vuuren | E26: Trevor Botes | I26: Johann Roos | M26: Ishaan/Elizabth | Q26: Androilla/ Praxia
A27: Income | E27: Income | I27: Income | M27: Income | Q27: Income
A28: Date: | C28: Payment | E28: Date: | G28: Payment | I28: Date: | K28: Payment | M28: Date: | O28: Payment | Q28: Date: | S28: Payment
A29: 45962 | C29: 5600 | E29: 45962 | G29: 3750 | I29: 45962 | K29: 7000 | M29: 45962 | O29: 6650 | Q29: 45962 | S29: 5250
A30: 45971 | C30: 5600 | E30: 45971 | G30: 3750 | I30: 45971 | K30: 7000 | M30: 45968 | O30: 6650 | Q30: 45973 | S30: 5250
A31: 45978 | C31: 5600 | E31: 45978 | G31: 3750 | Q31: 45981 | S31: 5250
A32: 45985 | C32: 3200 | E32: 45985 | G32: 3750 | Q32: 45987 | S32: 5250
A33: 45987 | C33: 3200
C34: =SUM(C29:C33) | G34: =SUM(G29:G32) | K34: =SUM(K29:K32) | O34: =SUM(O29:O32) | S34: =SUM(S29:S32)
A35: Expenses | E35: Expenses | I35: Expenses | M35: Expenses | Q35: Expenses
A36: Date: | B36: Expense Name | C36: Amount | E36: Date: | F36: Expense Name | G36: Amount | I36: Date: | J36: Expense Name | K36: Amount | M36: Date: | N36: Expense Name | O36: Amount | Q36: Date: | R36: Expense Name | S36: Amount
A37: 45962 | B37: Merriam | C37: 4500 | E37: 45962 | F37: Siphilisiwe (Patrica) | G37: 8450 | I37: 45962 | J37: Sylvia Nene | K37: 7000 | M37: 45962 | N37: Chrsitina | O37: 6300 | Q37: 45962 | R37: Sophia | S37: 11250
A38: 45962 | B38: Jane | C38: 6300
A49: Total Expense | C49: =SUM(C37:C48) | E49: Total Expense | G49: =SUM(G37:G48) | I49: Total Expense | K49: =SUM(K37:K48) | M49: Total Expense | O49: =SUM(O37:O48) | Q49: Total Expense | S49: =SUM(S37:S48)
A50: Income - Expense | C50: =MIN(C34-C49) | E50: Income - Expense | G50: =MIN(G34-G49) | I50: Income - Expense | K50: =MIN(K34-K49) | M50: Income - Expense | O50: =MIN(O34-O49) | Q50: Income - Expense | S50: =MIN(S34-S49)
A52: Jacomina/Charl | E52: Herman/Rene | I52: Lorraine Hatton | M52: Johanna Van Heerden | Q52: Dirk Le Roux
A53: Income | E53: Income | I53: Income | M53: Income | Q53: Income
A54: Date: | C54: Payment | E54: Date: | G54: Payment | I54: Date: | K54: Payment | M54: Date: | O54: Payment | Q54: Date: | S54: Payment
A55: 45962 | C55: 3800 | E55: 45966 | G55: 1700 | I55: 45977 | K55: 850 | M55: 45985 | O55: 4500 | Q55: 45992 | S55: 3000
E56: 45968 | G56: 2550 | I56: 45978 | K56: 850
C58: =SUM(C55:C57) | G58: =SUM(G55:G57) | K58: =SUM(K55:K57) | O58: =SUM(O55:O57)
A59: Expenses | E59: Expenses | I59: Expenses | M59: Expenses | S59: =SUM(S55:S58)
A60: Date: | B60: Expense Name | C60: Amount | E60: Date: | F60: Expense Name | G60: Amount | I60: Date: | J60: Expense Name | K60: Amount | M60: Date: | N60: Expense Name | O60: Amount | Q60: Expenses
A61: 45962 | B61: Refileo | C61: 4050 | E61: 45962 | F61: Joyce | G61: 2250 | I61: 45962 | J61: Sylvia Mutavhatsindi | K61: 750 | M61: 45962 | N61: Christina | O61: 2700 | Q61: Date: | R61: Expense Name | S61: Amount
A62: 45962 | B62: Susan | C62: 5850 | Q62: 45992
A73: Total Expense | C73: =SUM(C61:C72) | E73: Total Expense | G73: =SUM(G61:G72) | I73: Total Expense | K73: =SUM(K61:K72) | M73: Total Expense | O73: =SUM(O61:O72)
A74: Income - Expense | C74: =MIN(C58-C73) | E74: Income - Expense | G74: =MIN(G58-G73) | I74: Income - Expense | K74: =MIN(K58-K73) | M74: Income - Expense | O74: =MIN(O58-O73) | Q74: Total Expense
Q75: Income - Expense
A76: Mia Rus
A77: Income
A78: Date: | C78: Payment
A79: 45992 | C79: 12800
C82: =SUM(C79:C81)
A83: Expenses
A84: Date: | B84: Expense Name | C84: Amount
A85: 45992
A97: Total Expense
A98: Income - Expense
A104: Total from Clients | B104: =SUM(C8+G8+K8+O8+S8+C34+G34+K34+O34+S34+C58+G58+K58+O58+S59+C79)

Sheet Caregiver Nov 2025
C1: Linda Rapuluchukwa | D1: Sophie Koga | E1: Joyce Mutambiranwa | F1: Emily Mentula | G1: Cynthia Makondo | H1: Ruth Nnadi | I1: Christina Maluleka | J1: Mzee Mzwakhe | K1: Susan Murire | L1: Ndai Mapenyenye | M1: Adaobi Ejikeme | N1: Merriam Maluleke | O1: Jane Mokgaetsi Moekwa | P1: Sylvia Nene | Q1: Matodzi Sylvia Mutavhatsindi | R1: Siphilisiwe Nkala(Patricia) | S1: Refiloe Khuzwayo | T1: Mmamaswabi Emma Dhlamini | U1: Tracy Nothando Nyirenda
B2: Caregiver Price | C2: 600 | D2: 450 | E2: 450 | F2: 450 | G2: 350 | H2: 450 | I2: 450 | J2: 550 | K2: 450 | M2: 450 | N2: 450 | O2: 450 | P2: 350 | Q2: 450 | R2: 450 | S2: 450 | T2: 450 | U2: 450
A3: Date | B3: Days of Week
A4: 45962 | B4: Saturday | E4: Apie | G4: Hennie | I4: Elizabeth | K4: Jacomina | M4: Johnstons | O4: Linda | R4: Boets | U4: Hillery
A5: 45963 | B5: Sunday | E5: Apie | G5: Hennie | I5: Elizabeth | K5: Jacomina | M5: Johnstons | O5: Linda | U5: Hillery
A6: 45964 | B6: Monday | C6: Johnstons | F6: Apie | G6: Hennie | I6: Elizabeth | J6: Johan Bierman | K6: Jacomina | O6: Linda | P6: Roos | R6: Boets
A7: 45965 | B7: Tuesday | C7: Johnstons | F7: Apie | G7: Hennie | I7: Elizabeth | J7: Johan Bierman | K7: Jacomina | O7: Linda | P7: Roos | R7: Boets
A8: 45966 | B8: Wednesday | C8: Johnstons | E8: Rene | F8: Apie | I8: Elizabeth | J8: Johan Bierman | K8: Jacomina | O8: Linda | P8: Roos | R8: Boets
A9: 45967 | B9: Thursday | C9: Johnstons | D9: Androulla | E9: Rene | F9: Apie | G9: Hennie | I9: Elizabeth | J9: Johan Bierman | K9: Jacomina | O9: Linda | P9: Roos | R9: Boets
A10: 45968 | B10: Friday | D10: Androulla | E10: Rene | G10: Hennie | I10: Elizabeth | J10: Johan Bierman | K10: Jacomina | M10: Johnstons | O10: Van Vuuren | P10: Roos | R10: Boets | T10: Apie
A11: 45969 | B11: Saturday | D11: Androulla | E11: Rene | G11: Hennie | I11: Elizabeth | K11: Jacomina | M11: Johnstons | O11: Van Vuuren | T11: Apie
A12: 45970 | B12: Sunday | D12: Androulla | E12: Rene | I12: Elizabeth | M12: Johnstons | O12: Van Vuuren | S12: Jacomina | T12: Apie
A13: 45971 | B13: Monday | C13: Johnstons | D13: Androulla | F13: Apie | G13: Hennie | I13: Elizabeth | J13: Johan Bierman | O13: Van Vuuren | P13: Roos | R13: Boets | S13: Jacomina
A14: 45972 | B14: Tuesday | C14: Johnstons | D14: Androulla | F14: Apie | G14: Hennie | I14: Elizabeth | J14: Johan Bierman | O14: Van Vuuren | P14: Roos | R14: Boets | S14: Jacomina
A15: 45973 | B15: Wednesday | C15: Johnstons | D15: Androulla | F15: Apie | G15: Hennie | I15: Elizabeth | J15: Johan Bierman | O15: Van Vuuren | P15: Roos | R15: Boets | S15: Jacomina
A16: 45974 | B16: Thursday | C16: Johnstons | D16: Androulla | F16: Apie | G16: Hennie | I16: Elizabeth | J16: Johan Bierman | O16: Van Vuuren | P16: Roos | R16: Boets | S16: Jacomina
A17: 45975 | B17: Friday | D17: Androulla | G17: Hennie | J17: Johan Bierman | M17: Johnstons | N17: Van Vuuren | P17: Roos | R17: Boets | S17: Jacomina | T17: Apie
A18: 45976 | B18: Saturday | D18: Androulla | G18: Hennie | M18: Johnstons | N18: Van Vuuren | S18: Jacomina | T18: Apie
A19: 45977 | B19: Sunday | D19: Androulla | M19: Johnstons | N19: Van Vuuren | Q19: Hatton | S19: Jacomina | T19: Apie | U19: Hillery
A20: 45978 | B20: Monday | C20: Johnstons | D20: Androulla | G20: Hennie | J20: Johan Bierman | N20: Van Vuuren | P20: Roos | Q20: Hatton | R20: Boets | S20: Jacomina | T20: Apie
A21: 45979 | B21: Tuesday | C21: Johnstons | D21: Androulla | G21: Hennie | J21: Johan Bierman | K21: Jacomina | N21: Van Vuuren | P21: Roos | R21: Boets | T21: Apie
A22: 45980 | B22: Wednesday | C22: Johnstons | D22: Androulla | G22: Hennie | J22: Johan Bierman | K22: Jacomina | N22: Van Vuuren | P22: Roos | R22: Boets | T22: Apie
A23: 45981 | B23: Thursday | C23: Johnstons | D23: Androulla | G23: Hennie | J23: Johan Bierman | K23: Jacomina | N23: Van Vuuren | P23: Roos | R23: Boets | T23: Apie
A24: 45982 | B24: Friday | D24: Androulla | G24: Hennie | K24: Jacomina | M24: Johnstons | N24: Van Vuuren | P24: Roos | R24: Boets | T24: Apie
A25: 45983 | B25: Saturday | D25: Androulla | G25: Hennie | K25: Jacomina | M25: Johnstons | N25: Van Vuuren | T25: Apie
A26: 45984 | B26: Sunday | D26: Androulla | M26: Johnstons | N26: Van Vuuren | T26: Apie
A27: 45985 | B27: Monday | C27: Johnstons | D27: Androulla | G27: Hennie | J27: Johan Bierman | O27: Van Vuuren | P27: Roos | R27: Boets | T27: Apie
A28: 45986 | B28: Tuesday | C28: Johnstons | D28: Androulla | G28: Hennie | I28: Johanna | J28: Johan Bierman | O28: Van Vuuren | P28: Roos | R28: Boets | T28: Apie
A29: 45987 | B29: Wednesday | C29: Johnstons | D29: Androulla | G29: Hennie | I29: Johanna | J29: Johan Bierman | O29: Van Vuuren | P29: Roos | R29: Boets | T29: Apie
A30: 45988 | B30: Thursday | C30: Johnstons | D30: Androulla | G30: Hennie | I30: Johanna | J30: Johan Bierman | O30: Van Vuuren | P30: Roos | R30: Boets | T30: Apie
A31: 45989 | B31: Friday | D31: Androulla | G31: Hennie | I31: Johanna | J31: Johan Bierman | M31: Johnstons | O31: Van Vuuren | P31: Roos | R31: Boets | T31: Apie
A32: 45990 | B32: Saturday | D32: Androulla | G32: Hennie | I32: Johanna | M32: Johnstons | O32: Van Vuuren | T32: Apie | U32: Hillery
A33: 45991 | B33: Sunday | D33: Androulla | I33: Johanna | M33: Johnstons | O33: Van Vuuren | T33: Apie | U33: Hillery
A34: Days Worked | C34: 16 | D34: 25 | E34: 7 | F34: 8 | G34: 25 | I34: 20 | J34: 19 | K34: 13 | M34: 14 | N34: 10 | O34: 20 | P34: 20 | Q34: 2 | R34: 21 | S34: 9 | T34: 20 | U34: 5
A35: Money Borrowed | J35: 4000 | Q35: 150 | R35: 1000
A36: Total Amount | B36: =SUM(C36:U36) | C36: =C2*C34 | D36: =D2*D34 | E36: =E34*E2 | F36: =F34*F2 | G36: =G34*G2 | I36: =I2*I34 | J36: =J2*J34-J35 | K36: =K2*K34 | M36: =M2*M34 | N36: =N2*N34 | O36: =O2*O34 | P36: =P2*P34 | Q36: =Q2*Q34-Q35 | R36: =R2*R34-R35 | S36: =S2*S34 | T36: =T2*T34 | U36: =U2*U34
A39: Availble Caregiver | C39: =SUM(C36+D36+E36+F36+G36+I36+J36+K36+M36)
A40: Tabea
A41: Tracy
A42: Lerato | C42: =MIN(B36-C39)

Sheet Clients Dec 2025
A1: Johnstons | E1: Van Der Linde | I1: Hennie | M1: John Bierman | Q1: Hillery
A2: Income | E2: Income | I2: Income | M2: Income | Q2: Income
A3: Date: | C3: Payment | E3: Date: | G3: Payment | I3: Date: | K3: Payment | M3: Date: | O3: Payment | Q3: Date: | S3: Payment
A4: 45992 | B4: invoiced | C4: 24800 | E4: 45992 | F4: invoiced | G4: 22200 | I4: 45996 | J4: invoiced | K4: 4650 | M4: 45992 | N4: invoiced | O4: 18400 | Q4: 45993 | R4: invoiced | S4: 2850
C8: =SUM(C4:C7) | G8: =SUM(G4:G7) | K8: =SUM(K4:K7) | O8: =SUM(O4:O7) | S8: =SUM(S4:S7)
A9: Expenses | E9: Expenses | I9: Expenses | M9: Expenses | Q9: Expenses
A10: Date: | B10: Expense Name | C10: Amount | E10: Date: | F10: Expense Name | G10: Amount | I10: Date: | J10: Expense Name | K10: Amount | M10: Date: | N10: Expense Name | O10: Amount | Q10: Date: | R10: Expense Name | S10: Amount
A11: 45992 | B11: Linda | C11: 9600 | E11: 45992 | F11: Emily | G11: 9450 | I11: 45992 | J11: Cynthia | K11: 4200 | M11: 45992 | N11: Mzee | O11: 9400 | Q11: 1 dce | R11: Tracy | S11: 1800
A12: 45992 | B12: Ada | C12: 6750 | E12: 45992 | F12: Emma | G12: 4500 | I12: 45992 | J12: Uber | K12: 1216
E13: 45992 | F13: Uber | G13: 1589
A23: Total Expense | C23: =SUM(C11:C22) | E23: Total Expense | G23: =SUM(G11:G22) | I23: Total Expense | K23: =SUM(K11:K22) | M23: Total Expense | O23: =SUM(O11:O22) | Q23: Total Expense | S23: =SUM(S11:S22)
A24: Income - Expense | C24: =MIN(C4-C23) | E24: Income - Expense | G24: =MIN(G4-G23) | I24: Income - Expense | K24: =MIN(K4-K23) | M24: Income - Expense | O24: =MIN(O4-O23) | Q24: Income - Expense | S24: =MIN(S4-S23)
A26: Julian Sam | E26: Trevor Botes | I26: Johann Roos | M26: Dirk Le Roux | Q26: Androilla/ Praxia
A27: Income | E27: Income | I27: Income | M27: Income | Q27: Income
A28: Date: | C28: Payment | E28: Date: | G28: Payment | I28: Date: | K28: Payment | M28: Date: | O28: Payment | Q28: Date: | S28: Payment
A29: 45996 | B29: invoiced | C29: 5250 | E29: 45996 | F29: invoiced | G29: 3750 | I29: 45992 | J29: 1 Dec -12 Dec | K29: 7000 | M29: 46000 | N29: invoiced | O29: 5900 | Q29: 45992 | R29: invoiced | S29: 5250
A30: 46003 | B30: invoiced | C30: 5250 | E30: 46003 | F30: invoiced | G30: 3750 | I30: 46002 | J30: Invocied | K30: 4900 | M30: 46006 | N30: invoiced | O30: 4950 | Q30: 46000 | R30: invoiced | S30: 2250
A31: 46010 | C31: 4750 | E31: 46010 | F31: invoiced | G31: 3000
A32: 46017 | E32: 46017 | F32: invoiced | G32: 3000
E33: 46020 | F33: invoiced | G33: 3000
C34: =SUM(C29:C32) | G34: =SUM(G29:G33) | K34: =SUM(K29:K33) | O34: =SUM(O29:O32) | S34: =SUM(S29:S32)
A35: Expenses | E35: Expenses | I35: Expenses | M35: Expenses | Q35: Expenses
A36: Date: | B36: Expense Name | C36: Amount | E36: Date: | F36: Expense Name | G36: Amount | I36: Date: | J36: Expense Name | K36: Amount | M36: Date: | N36: Expense Name | O36: Amount | Q36: Date: | R36: Expense Name | S36: Amount
A37: 45992 | B37: Reflioe | C37: 6300 | E37: 45992 | F37: Siphilisiwe (Patrica) | G37: 8750 | I37: 45992 | J37: Sylvia Nene | K37: 5150 | M37: 45992 | N37: Ruth | O37: 6750 | Q37: 45962 | R37: Sophia | S37: 5850
A38: 45992 | B38: Siphethokhuhle | C38: 3150
A49: Total Expense | C49: =SUM(C37:C48) | E49: Total Expense | G49: =SUM(G37:G48) | I49: Total Expense | K49: =SUM(K37:K48) | M49: Total Expense | O49: =SUM(O37:O48) | Q49: Total Expense | S49: =SUM(S37:S48)
A50: Income - Expense | C50: =MIN(C34-C49) | E50: Income - Expense | G50: =MIN(G34-G49) | I50: Income - Expense | K50: =MIN(K34-K49) | M50: Income - Expense | O50: =MIN(O34-O49) | Q50: Income - Expense | S50: =MIN(S34-S37)
A52: Lucy | E52: Mia Rus | I52: Johanna Van Heerden | M52: Andre Theron | Q52: Angela/ Dimitri Paoadopoulos
A53: Income | E53: Income | I53: Income | M53: Income | Q53: Income
A54: Date: | C54: Payment | E54: Date: | G54: Payment | I54: Date: | K54: Payment | M54: Date: | O54: Payment | Q54: Date: | S54: Payment
A55: 46001 | B55: invoiced | C55: 2250 | E55: 45992 | G55: 9387 | I55: 45992 | J55: invoiced | K55: 23250 | M55: 45992 | N55: invoiced | O55: 5250 | Q55: 46008 | R55: invoiced | S55: 13300
A56: 46006 | B56: invoiced | C56: 3000 | M56: 46006 | N56: invoiced | O56: 10700
C59: =SUM(C55:C58) | G59: =SUM(G55:G58) | K59: =SUM(K55:K58) | O59: =SUM(O55:O58) | S59: =SUM(S55:S58)
A60: Expenses | E60: Expenses | I60: Expenses | M60: Expenses | Q60: Expenses
A61: Date: | B61: Expense Name | C61: Amount | E61: Date: | F61: Expense Name | G61: Amount | I61: Date: | J61: Expense Name | K61: Amount | M61: Date: | N61: Expense Name | O61: Amount | Q61: Date: | R61: Expense Name | S61: Amount
B62: Joyce | C62: 3150 | E62: 45992 | F62: Marion | G62: 4950 | I62: 45992 | J62: Christina | K62: 9450 | M62: 45992 | N62: Rebecca | O62: 2700 | Q62: 45992 | R62: Tracy | S62: 5850
J63: Jane | K63: 4500 | M63: 45992 | N63: Sophia | O63: 3600
M64: 45992 | N64: Joyce | O64: 3159
A74: Total Expense | C74: =SUM(C62:C72) | E74: Total Expense | G74: =SUM(G62:G66) | I74: Total Expense | K74: =SUM(K62:K73) | M74: Total Expense | O74: =SUM(O62:O73) | Q74: Total Expense | S74: =SUM(S62:S67)
A75: Income - Expense | C75: =MIN(C59-C74) | E75: Income - Expense | G75: =MIN(G59-G74) | I75: Income - Expense | K75: =MIN(K59-K74) | M75: Income - Expense | O75: =MIN(O59-O74) | Q75: Income - Expense | S75: =MIN(S59-S74)
A77: Marlanie | E77: Scroope | I77: Nozi | M77: Trish
A78: Income | E78: Income | I78: Income | M78: Income
A79: Date: | C79: Payment | E79: Date: | G79: Payment | I79: Date: | K79: Payment | M79: Date: | O79: Payment
A80: 46001 | B80: invoiced | C80: 1800 | E80: 46001 | F80: invoiced | G80: 14800 | I80: 46001 | J80: invoiced | K80: 3150 | M80: 46001 | N80: invoiced | O80: 1500
C84: =SUM(C80:C83) | G84: =SUM(G80:G83) | K84: =SUM(K80:K83) | O84: =SUM(O80:O83)
A85: Expenses | E85: Expenses | I85: Expenses | M85: Expenses
A86: Date: | B86: Expense Name | C86: Amount | E86: Date: | F86: Expense Name | G86: Amount | I86: Date: | J86: Expense Name | K86: Amount | M86: Date: | N86: Expense Name | O86: Amount
B87: Marion | C87: 450 | F87: Merriam | G87: 7000 | J87: Jane | K87: 1350 | N87: Marion | O87: 600
A99: Total Expense | C99: =SUM(C87:C92) | E99: Total Expense | G99: =SUM(G87:G90) | I99: Total Expense | K99: =SUM(K87:K91) | M99: Total Expense | O99: =SUM(O87:O91)
A100: Income - Expense | C100: =MIN(C84-C99) | E100: Income - Expense | G100: =MIN(G84-G99) | I100: Income - Expense | K100: =MIN(K84-K99) | M100: Income - Expense | O100: =MIN(O84-O99)
A102: Total from Clients | B102: =SUM(C8+G8+K8+O8+S8+C34+G34+K34+O34+S34+C59+G59+K59+O59+C84+G84+K84+O84+S59)
A104: Income - Expense | B104: =SUM(C24+G24+K24+O24+S24+C50+G50+K50+O50+S50+C75+G75+K75+O75+S75+C100+G100+K100+O100)

Sheet Caregiver Dec 2025
C1: Linda Rapuluchukwa | D1: Sophie Koga | E1: Joyce Mutambiranwa | F1: Emily Mentula | G1: Cynthia Makondo | H1: Ruth Nnadi | I1: Christina Maluleka | J1: Mzee Mzwakhe | K1: Susan Murire | L1: Ndai Mapenyenye | M1: Adaobi Ejikeme | N1: Merriam Maluleke | O1: Jane Mokgaetsi Moekwa | P1: Sylvia Nene | Q1: Matodzi Sylvia Mutavhatsindi | R1: Siphilisiwe Nkala(Patricia) | S1: Refiloe Khuzwayo | T1: Mmamaswabi Emma Dhlamini | U1: Tracy Nothando Nyirenda | V1: Marion Goeda | W1: Rebecca Samba | X1: Siphethokhuhle Nkomo
B2: Caregiver Price | C2: 600 | D2: 450 | E2: 450 | F2: 450 | G2: 350 | H2: 450 | I2: 450 | K2: 450 | M2: 450 | N2: 334 | O2: 450 | P2: 305 | Q2: 450 | R2: 450 | S2: 450 | T2: 450 | U2: 450 | V2: 450 | W2: 450 | X2: 450
A3: Date | B3: Days of Week
A4: 45992 | B4: Monday | C4: Johnstons | D4: Androulla | G4: Hennie | I4: Van Heerden | J4: Bierman | O4: Van Vuuren | P4: Roos | R4: Botes | T4: Apie | U4: Hillery
A5: 45993 | B5: Tuesday | C5: Johnstons | D5: Androulla | F5: Apie | G5: Hennie | I5: Van Heerden | J5: Bierman | P5: Roos | R5: Botes
A6: 45994 | B6: Wednesday | C6: Johnstons | D6: Androulla | F6: Apie | G6: Hennie | I6: Van Heerden | J6: Bierman | P6: Roos | R6: Botes
A7: 45995 | B7: Thursday | C7: Johnstons | D7: Androulla | F7: Apie | G7: Hennie | H7: Le Roux | I7: Van Heerden | J7: Bierman | P7: Roos | R7: Botes
A8: 45996 | B8: Friday | D8: Androulla | F8: Apie | G8: Hennie | I8: Van Heerden | J8: Bierman | M8: Johnstons | P8: Roos | R8: Botes
A9: 45997 | B9: Saturday | D9: Androulla | F9: Apie | G9: Hennie | I9: Van Heerden | M9: Johnstons
A10: 45998 | B10: Sunday | D10: Androulla | F10: Apie | I10: Van Heerden | M10: Johnstons | U10: Hillery
A11: 45999 | B11: Monday | D11: Androulla | F11: Apie | G11: Hennie | I11: Van Heerden | J11: Bierman | M11: Johnstons | P11: Roos | R11: Botes | S11: Sui Fon
A12: 46000 | B12: Tuesday | D12: Androulla | F12: Apie | G12: Hennie | I12: Van Heerden | J12: Bierman | M12: Johnstons | P12: Roos | R12: Botes | S12: Sui Fon
A13: 46001 | B13: Wednesday | C13: Johnstons | D13: Androulla | F13: Apie | G13: Hennie | H13: Le Roux | I13: Van Heerden | J13: Bierman | P13: Roos | R13: Botes | S13: Sui Fon | V13: Ras
A14: 46002 | B14: Thursday | C14: Johnstons | D14: Androulla | F14: Apie | G14: Hennie | H14: Le Roux | I14: Van Heerden | J14: Bierman | P14: Roos | R14: Botes | S14: Sui Fon | V14: Ras | W14: Theron
A15: 46003 | B15: Friday | C15: Johnstons | D15: Androulla | E15: Patricia | G15: Hennie | H15: Le Roux | I15: Van Heerden | J15: Bierman | P15: Roos | R15: Botes | S15: Sui Fon | T15: Apie | W15: Theron
A16: 46004 | B16: Saturday | C16: Johnstons | D16: Androulla | E16: Patricia | G16: Hennie | H16: Le Roux | I16: Van Heerden | S16: Sui Fon | T16: Apie | U16: Hillery | W16: Theron
A17: 46005 | B17: Sunday | C17: Johnstons | E17: Patricia | H17: Le Roux | I17: Van Heerden | S17: Sui Fon | T17: Apie | U17: Hillery | W17: Theron
A18: 46006 | B18: Monday | E18: Patricia | F18: Apie | H18: Le Roux | J18: Bierman | M18: Johnstons | O18: Van Heerden | P18: Roos | R18: Botes | S18: Sui Fon | W18: Theron
A19: 46007 | B19: Tuesday | E19: Patricia | F19: Apie | H19: Le Roux | J19: Bierman | M19: Johnstons | O19: Van Heerden | P19: Roos | S19: Sui Fon | W19: Theron
A20: 46008 | B20: Wednesday | D20: Theron | E20: Patricia | F20: Apie | H20: Le Roux | J20: Bierman | M20: Johnstons | O20: Van Heerden | P20: Roos | R20: Botes | S20: Sui Fon | V20: Ras
A21: 46009 | B21: Thursday | D21: Theron | E21: Patricia | F21: Apie | H21: Le Roux | J21: Bierman | M21: Johnstons | O21: Van Heerden | P21: Roos | R21: Botes | S21: Sui Fon | U21: Paoadopoulos | V21: Malanie
A22: 46010 | B22: Friday | C22: Johnstons | D22: Theron | H22: Le Roux | J22: Bierman | O22: Van Heerden | P22: Roos | R22: Botes | S22: Sui Fon | T22: Apie | U22: Paoadopoulos | V22: Ras
A23: 46011 | B23: Saturday | C23: Johnstons | D23: Theron | H23: Le Roux | O23: Van Heerden | R23: Botes | S23: Sui Fon | T23: Apie | U23: Paoadopoulos | V23: Ras
A24: 46012 | B24: Sunday | C24: Johnstons | D24: Theron | H24: Le Roux | O24: Van Heerden | S24: Sui Fon | T24: Apie | U24: Paoadopoulos | V24: Ras
A25: 46013 | B25: Monday | C25: Johnstons | D25: Theron | H25: Le Roux | I25: Van Heerden | J25: Bierman | N25: Scroope | P25: Roos | R25: Botes | T25: Apie | U25: Paoadopoulos | V25: Ras | X25: Sui Fon
A26: 46014 | B26: Tuesday | D26: Theron | F26: Apie | H26: Le Roux | I26: Van Heerden | J26: Bierman | M26: Johnstons | N26: Scroope | P26: Roos | R26: Botes | U26: Paoadopoulos | V26: Ras | X26: Sui Fon
A27: 46015 | B27: Wednesday | E27: Theron | F27: Apie | I27: Van Heerden | J27: Bierman | M27: Johnstons | N27: Scroope | O27: Nozi | R27: Botes | U27: Paoadopoulos | X27: Sui Fon
A28: 46016 | B28: Thursday | E28: Theron | F28: Apie | I28: Van Heerden | J28: Bierman | M28: Johnstons | N28: Scroope | O28: Nozi | U28: Paoadopoulos
A29: 46017 | B29: Friday | E29: Theron | F29: Apie | I29: Van Heerden | J29: Bierman | M29: Johnstons | N29: Scroope | O29: Nozi | U29: Paoadopoulos | V29: Trish-600
A30: 46018 | B30: Saturday | E30: Theron | F30: Apie | I30: Van Heerden | M30: Johnstons | N30: Scroope | U30: Paoadopoulos | X30: Sui Fon
A31: 46019 | B31: Sunday | E31: Theron | F31: Apie | I31: Van Heerden | M31: Johnstons | N31: Scroope | U31: Paoadopoulos | X31: Sui Fon
A32: 46020 | B32: Monday | C32: Johnstons | E32: Theron | F32: Apie | J32: Bierman | N32: Scroope | O32: Van Heerden | R32: Botes | U32: Paoadopoulos | V32: Ras | X32: Sui Fon
A33: 46021 | B33: Tuesday | C33: Johnstons | E33: Theron | J33: Bierman | N33: Scroope | O33: Van Heerden | R33: Botes | T33: Apie | U33: Paoadopoulos | V33: Ras | X33: Sui Fon
A34: 46022 | B34: Wednesday | C34: Johnstons | D34: Theron | E34: Paoadopoulos | J34: Bierman | N34: Scroope | O34: Van Heerden | R34: Botes | T34: Apie | V34: Ras
A35: Days Worked | C35: 16 | D35: 21 | E35: 15 | F35: 21 | G35: 12 | H35: 15 | I35: 21 | J35: 23 | M35: 15 | N35: 10 | O35: 14 | P35: 17 | R35: 21 | S35: 14 | T35: 10 | U35: 17 | V35: 13 | W35: 6 | X35: 7
V36: 150
A37: Money Borrowed | J37: 1600 | O37: 272 | R37: 700 | U37: 250 | V37: 1000 | W37: 2550
A38: Total Amount | B38: =SUM(C38:AL38) | C38: =C2*C35 | D38: =D2*D35 | E38: =E35*E2 | F38: =F35*F2 | G38: =G35*G2 | H38: =H2*H35 | I38: =I2*I35 | J38: 9400 | K38: =K2*K35 | M38: =M2*M35 | N38: =N2*N35 | O38: =O2*O35-O37 | P38: =P2*P35 | Q38: =Q2*Q35-Q37 | R38: =R2*R35-R37 | S38: =S2*S35 | T38: =T2*T35 | U38: =U2*U35-U37 | V38: =SUM(V2*V35-V37+V36) | W38: =W2*W35-W37 | X38: =X2*X35-X37
D41: Andre NPC | E41: =SUM(C38+D38+E38+F38+G38+H38+I38+J38+K38+L38+M38+W38)
D42: Donnay TCH | E42: =SUM(N38+O38+P38+Q38+R38+S38+T38+U38+V38+X38)

Sheet Clients Jan 2026
A1: Johnstons- monthly | E1: Van Der Linde- monthly | I1: Rene Lotz/ Wilhelm | M1: John Bierman- monthly | Q1: Natasha Naranjee | U1: Scroope
A2: Income | E2: Income | I2: Income | M2: Income | Q2: Income | U2: Income
A3: Date: | C3: Payment | E3: Date: | G3: Payment | I3: Date: | K3: Payment | M3: Date: | O3: Payment | Q3: Date: | S3: Payment | U3: Date: | W3: Payment
A4: 45658 | B4: Invoiced NPC | C4: 23250 | E4: 45658 | F4: Invoiced NPC | G4: 22200 | I4: 46030 | J4: invoiced | K4: 7300 | M4: 45658 | N4: Invoiced TCH | O4: 17600 | Q4: 46029 | R4: Invoived | S4: 3400 | U4: 46023 | V4: invoiced | W4: 1500
I5: 46038 | J5: invoiced | K5: 5900 | Q5: 46032 | R5: Invoived | S5: 6600 | U5: 46048 | V5: invoiced | W5: 2500
C8: =SUM(C4:C7) | G8: =SUM(G4:G7) | K8: =SUM(K4:K7) | O8: =SUM(O4:O7) | S8: =SUM(S4:S7) | W8: =SUM(W4:W7)
A9: Expenses | E9: Expenses | I9: Expenses | M9: Expenses | Q9: Expenses | U9: Expenses
A10: Date: | B10: Expense Name | C10: Amount | E10: Date: | F10: Expense Name | G10: Amount | I10: Date: | J10: Expense Name | K10: Amount | M10: Date: | N10: Expense Name | O10: Amount | Q10: Date: | R10: Expense Name | S10: Amount | U10: Date: | V10: Expense Name | W10: Amount
A11: 45992 | B11: Linda | E11: 45992 | F11: Emily | M11: 45992 | Q11: 46023 | R11: Marion | V11: Merriam
A12: 45992 | B12: Ada | E12: 45992 | F12: Emma | R12: Syliva Nene
B13: Sylive | E13: 45992 | F13: Uber | R13: Joyce
A23: Total Expense | C23: =SUM(C11:C22) | E23: Total Expense | G23: =SUM(G11:G22) | I23: Total Expense | K23: =SUM(K11:K22) | M23: Total Expense | O23: =SUM(O11:O22) | Q23: Total Expense | S23: =SUM(S11:S22) | U23: Total Expense | W23: =SUM(W11:W14)
A24: Income - Expense | C24: =MIN(C4-C23) | E24: Income - Expense | G24: =MIN(G4-G23) | I24: Income - Expense | K24: =MIN(K4-K23) | M24: Income - Expense | O24: =MIN(O4-O23) | Q24: Income - Expense | S24: =MIN(S4-S23) | U24: Income - Expense | W24: =MIN(W8-W23)
A26: Julian Sam | E26: Trevor Botes- monthly | I26: Johann Roos | M26: Dirk Le Roux- monthly | Q26: Kotie Jacoba | U26: Christina Botha (Transfer)
A27: Income | E27: Income | I27: Income | M27: Income | Q27: Income | U27: Income
A28: Date: | C28: Payment | E28: Date: | G28: Payment | I28: Date: | K28: Payment | M28: Date: | O28: Payment | Q28: Date: | S28: Payment | U28: Date: | W28: Payment
A29: 45658 | B29: Invoiced | C29: 2036 | E29: 45662 | F29: invoiced | G29: 14250 | M29: 45658 | N29: invoiced TCH | O29: 3750 | Q29: 45658 | R29: invocied | S29: 3850 | U29: 46037 | W29: 700
A30: 46027 | B30: Invoiced | C30: 3393 | Q30: 45662 | R30: invoiced | S30: 3750
A31: 46030 | B31: Invoiced | C31: 2715 | Q31: 46030 | R31: invocied | S31: 600
A32: 46046 | B32: Invoiced | C32: 2036
C33: =SUM(C29:C32) | G33: =SUM(G29:G32) | K33: =SUM(K29:K32) | O33: =SUM(O29:O32) | S33: =SUM(S29:S32) | W33: =SUM(W29:W32)
A34: Expenses | E34: Expenses | I34: Expenses | M34: Expenses | Q34: Expenses | U34: Expenses
A35: Date: | B35: Expense Name | C35: Amount | E35: Date: | F35: Expense Name | G35: Amount | I35: Date: | J35: Expense Name | K35: Amount | M35: Date: | N35: Expense Name | O35: Amount | Q35: Date: | R35: Expense Name | S35: Amount | U35: Date: | V35: Expense Name | W35: Amount
A36: 45992 | B36: Siphe | E36: 45992 | F36: Siphilisiwe (Patrica) | I36: 45992 | M36: 45992 | Q36: 45658 | U36: 45658 | V36: Lina
A37: 45992
A48: Total Expense | C48: =SUM(C36:C47) | E48: Total Expense | G48: =SUM(G36:G47) | I48: Total Expense | M48: Total Expense | Q48: Total Expense | S48: 14838 | U48: Total Expense | W48: 14838
A49: Income - Expense | C49: =MIN(C29-C48) | E49: Income - Expense | G49: =MIN(G29-G48) | I49: Income - Expense | M49: Income - Expense | Q49: Income - Expense | S49: 7362 | U49: Income - Expense | W49: 7362
A51: Julia Ann | E51: Mia Rus- monthly | I51: Johanna Van Heerden- monthly | M51: Andre Theron- monthly | Q51: Angela/ Dimitri Paoadopoulos- weekly | U51: Du Plessis
A52: Income | E52: Income | I52: Income | M52: Income | Q52: Income | U52: Income
A53: Date: | C53: Payment | E53: Date: | G53: Payment | I53: Date: | K53: Payment | M53: Date: | O53: Payment | Q53: Date: | S53: Payment | U53: Date: | W53: Payment
A54: 46027 | B54: invoiced | C54: 6000 | E54: 46029 | F54: invoiced | G54: 11900 | I54: 45658 | J54: Invoiced TCH | K54: 23250 | M54: 45658 | N54: invoiced | O54: 5450 | Q54: 45658 | R54: invoiced | S54: 6650 | U54: 46042 | V54: invoiced | W54: 5114
A55: 46031 | B55: invoiced | C55: 12000 | M55: 46030 | N55: invoiced | O55: 12750 | Q55: 46030 | R55: invoiced | S55: 6650
Q56: 46034 | R56: invoiced | S56: 6650
Q57: 46044 | R57: invoiced | S57: 6650
Q58: 46051 | R58: invoiced | S58: 6650
C59: =SUM(C54:C57) | G59: =SUM(G54:G58) | K59: =SUM(K54:K57) | O59: =SUM(O54:O57) | S59: =SUM(S54:S58) | W59: =SUM(W54:W57)
A60: Expenses | E60: Expenses | I60: Expenses | M60: Expenses | Q60: Expenses | U60: Expenses
A61: Date: | B61: Expense Name | C61: Amount | E61: Date: | F61: Expense Name | G61: Amount | I61: Date: | J61: Expense Name | K61: Amount | M61: Date: | N61: Expense Name | O61: Amount | Q61: Date: | R61: Expense Name | S61: Amount | U61: Date: | V61: Expense Name | W61: Amount
A62: 46023 | B62: Cynthia | E62: 45992 | F62: Marion | I62: 45658 | J62: Christina | M62: 45658 | N62: Sophia | Q62: 45992 | R62: Tracy | U62: 45658
B63: Jane | I63: 45658 | J63: Lina | M63: 45658 | R63: Joyce
A74: Total Expense | E74: Total Expense | I74: Total Expense | M74: Total Expense | Q74: Total Expense | U74: Total Expense
A75: Income - Expense | E75: Income - Expense | I75: Income - Expense | M75: Income - Expense | Q75: Income - Expense | U75: Income - Expense
A77: Megan Barnes | E77: Darren Blumenthal
A78: Income | E78: Income
A79: Date: | C79: Payment | E79: Date: | G79: Payment
A80: 46046 | B80: invoiced | C80: 3250 | E80: 46046 | F80: invoiced | G80: 1800
E81: 46046 | F81: invoiced | G81: 900
C85: =SUM(C80:C83) | G85: =SUM(G80:G83)
A86: Expenses | E86: Expenses
A87: Date: | B87: Expense Name | C87: Amount | E87: Date: | F87: Expense Name | G87: Amount
A88: 46023 | B88: Cynthia | E88: 46050 | F88: Nipho
A100: Total Expense | E100: Total Expense
A101: Income - Expense | E101: Income - Expense
A107: Total from Clients | B107: =SUM(C8+G8+K8+O8+S8+C33+G33+K33+O33+S33+C59+G59+K59+O59+W8+S59+W59+W33+C85+G85)

Sheet Caregiver Jan 2026
C1: Linda Rapuluchukwa | D1: Sophie Koga | E1: Joyce Mutambiranwa | F1: Emily Mentula | G1: Cynthia Makondo | H1: Ruth Nnadi | I1: Christina Maluleka | J1: Susan Murire | K1: Ndai Mapenyenye | L1: Adaobi Ejikeme | M1: Merriam Maluleke | N1: Jane Mokgaetsi Moekwa | O1: Sylvia Nene | P1: Matodzi Sylvia Mutavhatsindi | Q1: Siphilisiwe Nkala(Patricia) | R1: Refiloe Khuzwayo | S1: Mmamaswabi Emma Dhlamini | T1: Tracy Nothando Nyirenda | U1: Marion Goeda | V1: Siphethokhuhle Nkomo | W1: Lina Raphahlela | X1: Matshidiso Leah Aphane | Y1: Monique Bosch | Z1: Nhlakanipho (Nipho) Tshabalala
B2: Caregiver Price | C2: 600 | D2: 450 | E2: 500 | F2: 450 | G2: 450 | H2: 450 | I2: 450 | J2: 450 | L2: 450 | M2: 334 | N2: 450 | O2: 450 | P2: 450 | Q2: 450 | R2: 450 | S2: 450 | T2: 450 | U2: 450 | V2: 450 | W2: 450 | X2: 350 | Y2: 283 | Z2: 500
A3: Date | B3: Days of Week
A4: 45658 | B4: Thursday | C4: Johnstons | D4: Theron | E4: Paoadopoulos | H4: Le Roux | M4: Scroope | N4: Klientjie | S4: Apie | U4: Ras
A5: 45659 | B5: Friday | D5: Theron | E5: Paoadopoulos | L5: Johnstons | M5: Scroope | N5: Klientjie | S5: Apie | U5: Ras | V5: Sui Fon
A6: 45660 | B6: Saturday | D6: Theron | E6: Paoadopoulos | J6: Kotie- half | L6: Johnstons | M6: Scroope | N6: Klientjie | S6: Apie | U6: Ras | V6: Sui Fon
A7: 45661 | B7: Sunday | D7: Theron | E7: Paoadopoulos | L7: Johnstons | M7: Scroope | N7: Klientjie | S7: Apie | U7: Ras | V7: Sui Fon
A8: 45662 | B8: Monday | C8: Johnstons | D8: Theron | E8: Paoadopoulos | F8: Apie | G8: Julia Ann | I8: Klientjie | J8: Kotie | M8: Scroope | Q8: Boets | U8: Kotie | V8: Sui Fon
A9: 45663 | B9: Tuesday | C9: Johnstons | D9: Theron | E9: Paoadopoulos | F9: Apie | G9: Julia Ann | I9: Klientjie | M9: Scroope | Q9: Boets | V9: Sui Fon
A10: 45664 | B10: Wednesday | C10: Johnstons | D10: Theron | E10: Paoadopoulos | F10: Apie | G10: Julia Ann | I10: Klientjie | M10: Scroope | Q10: Boets | V10: Sui Fon
A11: 45665 | B11: Thursday | C11: Johnstons | D11: Theron | E11: Paoadopoulos | F11: Apie | G11: Julia Ann | H11: Le Roux | I11: Klientjie | M11: Scroope | Q11: Boets | U11: Natasha | V11: Sui Fon
A12: 45666 | B12: Friday | C12: Johnstons | D12: Theron | E12: Paoadopoulos | G12: Julia Ann | H12: Lotz | I12: Klientjie | M12: Scroope | O12: Johnstons | Q12: Boets | S12: Apie | U12: Natasha | V12: Sui Fon
A13: 45667 | B13: Saturday | E13: Paoadopoulos | H13: Lotz | I13: Klientjie | L13: Johnstons | M13: Scroope | N13: Julia Ann | S13: Apie | U13: Natasha
A14: 45668 | B14: Sunday | E14: Paoadopoulos | H14: Lotz | I14: Klientjie | L14: Johnstons | M14: Scroope | N14: Julia Ann | O14: Natasha | S14: Apie | U14: Natasha
A15: 45669 | B15: Monday | D15: Theron | F15: Apie | H15: Lotz | I15: Klientjie | J15: Bierman | L15: Johnstons | M15: Scroope-R450 | N15: Julia Ann | O15: Natasha | T15: Paoadopoulos | U15: Ras | V15: Sui Fon
A16: 45670 | B16: Tuesday | D16: Theron | F16: Apie | H16: Lotz | I16: Klientjie | J16: Bierman | L16: Johnstons | N16: Julia Ann | O16: Natasha | T16: Paoadopoulos | U16: Ras | V16: Sui Fon
A17: 45671 | B17: Wednesday | D17: Theron | E17: Natasha | F17: Apie | I17: Klientjie | J17: Bierman | L17: Johnstons | N17: Julia Ann | Q17: Boets | S17: Lotz | T17: Paoadopoulos | U17: Ras | V17: Sui Fon
A18: 45672 | B18: Thursday | C18: Johnstons | D18: Theron | E18: Natasha | F18: Apie | I18: Klientjie | J18: Bierman | N18: Julia Ann | Q18: Boets | S18: Lotz | T18: Paoadopoulos | U18: Ras | V18: Sui Fon | W18: Christina
A19: 45673 | B19: Friday | C19: Johnstons | D19: Theron | H19: Lotz | I19: Klientjie | J19: Bierman | N19: Julia Ann | Q19: Boets | S19: Apie | T19: Paoadopoulos | U19: Ras
A20: 45674 | B20: Saturday | C20: Johnstons | H20: Lotz | I20: Klientjie | N20: Julia Ann | S20: Apie | T20: Paoadopoulos | U20: Ras
A21: 45675 | B21: Sunday | C21: Johnstons | H21: Lotz | I21: Klientjie | N21: Julia Ann | S21: Apie | T21: Paoadopoulos | U21: Ras
A22: 45676 | B22: Monday | C22: Johnstons | D22: Theron | E22: Paoadopoulos | F22: Apie | H22: Lotz | I22: Klientjie | J22: Bierman | N22: Julia Ann | Q22: Boets
A23: 45677 | B23: Tuesday | C23: Johnstons | D23: Theron | E23: Paoadopoulos | F23: Apie | H23: Lotz | I23: Klientjie | J23: Bierman | O23: Johnstons | Q23: Boets | Y23: Du Plessis
A24: 45678 | B24: Wednesday | D24: Theron | E24: Paoadopoulos | F24: Apie | H24: Lotz | I24: Klientjie | J24: Bierman | O24: Johnstons | Q24: Boets | Y24: Du Plessis
A25: 45679 | B25: Thursday | D25: Theron | E25: Paoadopoulos | F25: Apie | H25: Le Roux | I25: Klientjie | J25: Bierman | O25: Johnstons | T25: Lotz | Y25: Du Plessis
A26: 45680 | B26: Friday | D26: Theron | E26: Paoadopoulos | F26: Apie | H26: Lotz | I26: Klientjie | J26: Bierman | O26: Johnstons | Q26: Boets | Y26: Du Plessis
A27: 45681 | B27: Saturday | E27: Paoadopoulos | F27: Apie | I27: Klientjie | O27: Johnstons
A28: 45682 | B28: Sunday | E28: Paoadopoulos | F28: Apie | I28: Klientjie | O28: Johnstons
A29: 45683 | B29: Monday | C29: Johnstons | D29: Theron | F29: Apie | J29: Bierman | Q29: Boets | T29: Paoadopoulos | U29: Ras | V29: Sui Fon | W29: Klientjie | X29: Barnes | Y29: Du Plessis
A30: 45684 | B30: Tuesday | C30: Johnstons | D30: Theron | F30: Apie | J30: Bierman | Q30: Boets | T30: Paoadopoulos | U30: Ras | W30: Klientjie | X30: Barnes | Y30: Du Plessis
A31: 45685 | B31: Wednesday | C31: Johnstons | D31: Theron | F31: Apie | J31: Bierman | Q31: Boets | T31: Paoadopoulos | U31: Ras | V31: Sui Fon | W31: Klientjie | X31: Barnes | Y31: Du Plessis | Z31: Blumenthal
A32: 45686 | B32: Thursday | C32: Johnstons | D32: Theron | F32: Apie | H32: Le Roux | J32: Bierman | Q32: Boets | T32: Paoadopoulos | U32: Ras | W32: Klientjie | X32: Barnes | Y32: Du Plessis | Z32: Blumenthal
A33: 45687 | B33: Friday | D33: Theron | G33: Scroope | J33: Bierman | M33: Scroope | O33: Johnstons | Q33: Boets | S33: Apie | T33: Paoadopoulos | U33: Ras | V33: Sui Fon | W33: Klientjie | X33: Barnes | Y33: Du Plessis | Z33: Blumenthal
A34: 45688 | B34: Saturday | G34: Scroope | M34: Scroope | O34: Johnstons | S34: Apie | T34: Paoadopoulos | U34: Ras | W34: Klientjie
A35: Days Worked | C35: 16 | D35: 24 | E35: 20 | F35: 19 | G35: 5 | H35: 16 | I35: 21 | J35: 16 | L35: 8 | M35: 11 | N35: 14 | O35: 12 | Q35: 17 | S35: 15 | T35: 14 | U35: 22 | V35: 16 | W35: 8 | X35: 5 | Y35: 9 | Z35: 5
A36: Money added | G36: 800 | J36: 225 | M36: 1250
A37: Money Borrowed | F37: 190 | O37: 50 | Q37: 700 | U37: 809
A38: Total Amount | B38: =SUM(C38:AJ38) | C38: =C2*C35 | D38: =D2*D35 | E38: =E35*E2 | F38: =F35*F2-F37 | G38: =G35*G2+G36 | H38: =H2*H35 | I38: =I2*I35 | J38: =J2*J35+J36 | L38: =L2*L35 | M38: =M2*M35+M36 | N38: =N2*N35 | O38: =O2*O35-O37 | P38: =P2*P35-P37 | Q38: =Q2*Q35-Q37 | R38: =R2*R35 | S38: =S2*S35 | T38: =T2*T35 | U38: =SUM(U2*U35-U37) | V38: =V2*V35-V37 | W38: =W2*W35 | X38: =X2*X35 | Y38: =Y2*Y35 | Z38: =Z2*Z35
B41: Tuniti NPC | C41: =SUM(C38:L38)
B42: TCH | C42: =SUM(M38:Z38)

Sheet Clients Feb 2026
A1: Johnstons- monthly | E1: Van Der Linde- monthly | I1: Rene Lotz/ Wilhelm | M1: John Bierman- monthly | Q1: Wessels | U1: Scroope
A2: Income | E2: Income | I2: Income | M2: Income | Q2: Income | U2: Income
A3: Date: | C3: Payment | E3: Date: | G3: Payment | I3: Date: | K3: Payment | M3: Date: | O3: Payment | Q3: Date: | S3: Payment | U3: Date: | W3: Payment
A4: 46054 | B4: Invoiced NPC | C4: 21000 | E4: 46054 | F4: Invoiced NPC | G4: 22200 | M4: 46054 | N4: Invoiced TCH | O4: 16000 | Q4: 46054 | R4: invoiced | S4: 3800 | U4: 46072 | V4: invoiced | W4: 3350
C8: =SUM(C4:C7) | G8: =SUM(G4:G7) | K8: =SUM(K4:K7) | O8: =SUM(O4:O7) | W8: =SUM(W4:W7)
A9: Expenses | E9: Expenses | I9: Expenses | M9: Expenses | Q9: Expenses | U9: Expenses
A10: Date: | B10: Expense Name | C10: Amount | E10: Date: | F10: Expense Name | G10: Amount | I10: Date: | J10: Expense Name | K10: Amount | M10: Date: | N10: Expense Name | O10: Amount | Q10: Date: | R10: Expense Name | S10: Amount | U10: Date: | V10: Expense Name | W10: Amount
A11: 46054 | B11: Linda | E11: 46054 | F11: Emily | M11: 46054 | N11: Susan | R11: Ruth | V11: Merriam
A12: 46054 | B12: Ada | E12: 46054 | F12: Emma
B13: Sylive | E13: 46054 | F13: Uber
A23: Total Expense | C23: =SUM(C11:C22) | E23: Total Expense | G23: =SUM(G11:G22) | I23: Total Expense | K23: =SUM(K11:K22) | M23: Total Expense | O23: =SUM(O11:O22) | Q23: Total Expense | S23: =SUM(S11:S22) | U23: Total Expense | W23: =SUM(W11:W14)
A24: Income - Expense | C24: =MIN(C4-C23) | E24: Income - Expense | G24: =MIN(G4-G23) | I24: Income - Expense | K24: =MIN(K4-K23) | M24: Income - Expense | O24: =MIN(O4-O23) | Q24: Income - Expense | S24: =MIN(S4-S23) | U24: Income - Expense | W24: =MIN(W8-W23)
A26: Julian Sam | E26: Trevor Botes- monthly | I26: Berthe Botha | M26: Dirk Le Roux- monthly | Q26: Angela/ Dimitri Paoadopoulos- weekly | U26: Du Plessis
A27: Income | E27: Income | I27: Income | M27: Income | Q27: Income | U27: Income
A28: Date: | C28: Payment | E28: Date: | G28: Payment | I28: Date: | K28: Payment | M28: Date: | O28: Payment | Q28: Date: | S28: Payment | U28: Date: | W28: Payment
A29: 46054 | B29: invoiced | C29: 2036 | E29: 45662 | F29: invoiced | G29: 13500 | I29: 46058 | J29: invoiced | K29: 5250 | M29: 46054 | N29: invoiced TCH | O29: 3000 | Q29: 46057 | R29: invoiced | S29: 6650 | U29: 46054 | V29: invoiced | W29: 12500
A30: 46061 | B30: invoiced | C30: 2036 | Q30: 46064 | R30: invoiced | S30: 6650 | U30: 46064 | V30: invoiced | W30: 1500
Q31: 46071 | R31: invoiced | S31: 6650
Q32: 46078 | S32: 6650
C33: =SUM(C29:C32) | G33: =SUM(G29:G32) | K33: =SUM(K29:K32) | O33: =SUM(O29:O32)
A34: Expenses | E34: Expenses | I34: Expenses | M34: Expenses | S34: =SUM(S29:S33) | W34: =SUM(W29:W32)
A35: Date: | B35: Expense Name | C35: Amount | E35: Date: | F35: Expense Name | G35: Amount | I35: Date: | J35: Expense Name | K35: Amount | M35: Date: | N35: Expense Name | O35: Amount | Q35: Expenses | U35: Expenses
A36: 46054 | B36: Siphe | E36: 46054 | F36: Siphilisiwe (Patrica) | I36: 46054 | J36: Emilia | M36: 46054 | N36: Ruth | Q36: Date: | R36: Expense Name | S36: Amount | U36: Date: | V36: Expense Name | W36: Amount
Q37: 45992 | R37: Tracy | U37: 45658 | V37: monique
R38: Musa | V38: Joyce
A48: Total Expense | C48: =SUM(C36:C47) | E48: Total Expense | G48: =SUM(G36:G47) | I48: Total Expense | M48: Total Expense | Q48: Total Expense | U48: Total Expense
A49: Income - Expense | C49: =MIN(C29-C48) | E49: Income - Expense | G49: =MIN(G29-G48) | I49: Income - Expense | M49: Income - Expense | Q49: Income - Expense | U49: Income - Expense
A51: Mia Ras- monthly | E51: Megan Barnes | I51: Johanna Van Heerden- monthly | M51: Andre Theron- monthly | Q51: Derek Halls | U51: Morrison
A52: Income | E52: Income | I52: Income | M52: Income | Q52: Income | U52: Income
A53: Date: | C53: Payment | E53: Date: | G53: Payment | I53: Date: | K53: Payment | M53: Date: | O53: Payment | Q53: Date: | S53: Payment | U53: Date: | W53: Payment
A54: 46054 | B54: invoiced | C54: 11900 | E54: 46054 | F54: invoiced | G54: 13000 | I54: 46054 | J54: Invoiced TCH | K54: 23250 | M54: 46054 | N54: invoiced | O54: 15000 | Q54: 46054 | R54: invoiced | S54: 15000 | U54: 46055 | V54: invoiced
M55: 46070 | N55: invoiced | O55: 3450 | Q55: 46069 | R55: invoiced | S55: 1500 | U55: 46062
U56: 46069
U57: 46076
C59: =SUM(C54:C58) | G59: =SUM(G54:G57) | K59: =SUM(K54:K57) | O59: =SUM(O54:O57) | S59: =SUM(S54:S57) | W59: =SUM(W54:W57)
A60: Expenses | E60: Expenses | I60: Expenses | M60: Expenses | Q60: Expenses | U60: Expenses
A61: Date: | B61: Expense Name | C61: Amount | E61: Date: | F61: Expense Name | G61: Amount | I61: Date: | J61: Expense Name | K61: Amount | M61: Date: | N61: Expense Name | O61: Amount | Q61: Date: | R61: Expense Name | S61: Amount | U61: Date: | V61: Expense Name | W61: Amount
A62: 46054 | B62: Marion | E62: 46023 | F62: Leah | I62: 46054 | J62: Christina | M62: 46054 | N62: Sophia | Q62: 46054 | R62: Busi | U62: 46054
I63: 46054 | J63: Ada | N63: Ndai | R63: Sara
A74: Total Expense | E74: Total Expense | I74: Total Expense | M74: Total Expense | Q74: Total Expense | U74: Total Expense
A75: Income - Expense | E75: Income - Expense | I75: Income - Expense | M75: Income - Expense | Q75: Income - Expense | U75: Income - Expense
A77: Kotie- Rental | E77: Scholtz | I77: Maria Burgum- Weekly | M77: Jean Place | Q77: Roux- Esme | U77: Carolina Richards
A78: Income | E78: Income | I78: Income | M78: Income | Q78: Income | U78: Income
A79: Date: | C79: Payment | E79: Date: | G79: Payment | I79: Date: | K79: Payment | M79: Date: | O79: Payment | Q79: Date: | S79: Payment | U79: Date: | W79: Payment
A80: 46054 | B80: invoiced | C80: 600 | E80: 46058 | F80: invoiced | G80: 3000 | I80: 46060 | J80: invoiced | K80: 2250 | M80: 46060 | N80: invoiced | O80: 4000 | Q80: 46062 | R80: invoiced | S80: 8250 | U80: 46063 | V80: invoiced | W80: 9750
I81: 46066 | J81: invoiced | K81: 2450 | M81: 46066 | N81: invoiced | O81: 2400 | U81: 46071 | V81: invoiced | W81: 1500
I82: 46076 | J82: invoiced | K82: 2250 | M82: 46074 | N82: invoiced | O82: 3200 | U82: 46078 | V82: invoiced | W82: 750
I83: 46079 | J83: invoiced | K83: 1050
C85: =SUM(C80:C84) | G85: =SUM(G80:G84) | K85: =SUM(K80:K84) | O85: =SUM(O80:O84) | S85: =SUM(S80:S84) | W85: =SUM(W80:W84)
A86: Expenses | E86: Expenses | I86: Expenses | M86: Expenses | Q86: Expenses | U86: Expenses
A87: Date: | B87: Expense Name | C87: Amount | E87: Date: | F87: Expense Name | G87: Amount | I87: Date: | J87: Expense Name | K87: Amount | M87: Date: | N87: Expense Name | O87: Amount | Q87: Date: | R87: Expense Name | S87: Amount | U87: Date: | V87: Expense Name | W87: Amount
F88: Martha Mashishi | J88: Martha Sone | N88: Nipho | R88: Julia | V88: Julia
F89: Mbali | J89: Syliva
A100: Total Expense | E100: Total Expense | I100: Total Expense | M100: Total Expense | Q100: Total Expense | U100: Total Expense
A101: Income - Expense | E101: Income - Expense | I101: Income - Expense | M101: Income - Expense | Q101: Income - Expense | U101: Income - Expense
A103: Webb- Sonja | E103: Oosthuizen- Weekly | I103: O'Neill | M103: De Waal
A104: Income | E104: Income | I104: Income | M104: Income
A105: Date: | C105: Payment | E105: Date: | G105: Payment | I105: Date: | K105: Payment | M105: Date: | O105: Payment
A106: 46064 | B106: invoiced | C106: 1450 | E106: 16 | F106: invoiced | G106: 3000 | I106: 46064 | J106: invoiced | K106: 6000 | M106: 46073 | N106: invoiced | O106: 5700
A107: 46078 | B107: invoiced | C107: 1500 | E107: 46075 | F107: invoiced | G107: 3750
C111: =SUM(C106:C110) | G111: =SUM(G106:G110) | K111: =SUM(K106:K110) | O111: =SUM(O106:O110)
A112: Expenses | E112: Expenses | I112: Expenses | M112: Expenses
A113: Date: | B113: Expense Name | C113: Amount | E113: Date: | F113: Expense Name | G113: Amount | I113: Date: | J113: Expense Name | K113: Amount | M113: Date: | N113: Expense Name | O113: Amount
B114: Ruth | F114: Marion | J114: Merriam | N114: Merriam
F115: Sara
A126: Total Expense | E126: Total Expense | I126: Total Expense | M126: Total Expense
A127: Income - Expense | E127: Income - Expense | I127: Income - Expense | M127: Income - Expense
A132: Total from Clients | B132: =SUM(C8+G8+K8+O8+S8+W8+C33+G33+K33+O33+S34+W34+C59+G59+K59+O59+S59+W59+C85+G85+K85+O85+S85+W85+C111+G111+K111+O111)

Sheet Caregiver Feb 2026
C1: Linda Rapuluchukwa | D1: Sophie Koga | E1: Joyce Mutambiranwa | F1: Emily Mentula | G1: Cynthia Makondo | H1: Ruth Nnadi | I1: Christina Maluleka | J1: Susan Murire | K1: Ndai Mapenyenye | L1: Adaobi Ejikeme | M1: Merriam Maluleke | N1: Jane Mokgaetsi Moekwa | O1: Sylvia Nene | P1: Matodzi Sylvia Mutavhatsindi | Q1: Siphilisiwe Nkala(Patricia) | R1: Refiloe Khuzwayo | S1: Mmamaswabi Emma Dhlamini | T1: Tracy Nothando Nyirenda | U1: Marion Goeda | V1: Siphethokhuhle Nkomo | W1: Lina Raphahlela | X1: Matshidiso Leah Aphane | Y1: Monique Bosch | Z1: Nhlakanipho (Nipho) Tshabalala | AA1: Musa Zulu | AB1: Busisiwe Mandiyanike | AC1: Emilia Masvosva | AD1: Martha Mashishi | AE1: Sara Mdaka | AF1: Martha Sona | AG1: Julia Ramoroka | AH1: Mbali Ndaba
B2: Caregiver Price | C2: 600 | D2: 450 | E2: 500 | F2: 450 | G2: 450 | H2: 450 | I2: 450 | J2: 450 | K2: 450 | L2: 450 | M2: 450 | N2: 450 | O2: 450 | P2: 450 | Q2: 450 | R2: 450 | S2: 450 | T2: 450 | U2: 450 | V2: 450 | W2: 450 | X2: 350 | Y2: 325 | Z2: 450 | AA2: 450 | AB2: 450 | AC2: 450 | AD2: 450 | AE2: 450 | AF2: 450 | AG2: 450 | AH2: 450
A3: Date | B3: Days of Week
A4: 46054 | B4: Sunday | G4: Scroope- R400 | O4: Johnstons | S4: Apie | T4: Papou | U4: Ras | W4: Klientjie
A5: 46055 | B5: Monday | C5: Johnstons | D5: Theron | F5: Apie | I5: Klientjie | J5: Bierman | Q5: Botes | V5: Sui Fon | X5: Barnes | Y5: Du Plessis | AA5: Papou | AB5: Cecily
A6: 46056 | B6: Tuesday | C6: Johnstons | D6: Theron | I6: Klientjie | J6: Bierman | Q6: Botes | S6: Apie | X6: Barnes | Y6: Du Plessis | AA6: Papou | AB6: Cecily
A7: 46057 | B7: Wednesday | C7: Johnstons | D7: Theron | E7: Du Plessis | H7: Wessels | I7: Klientjie | J7: Bierman | Q7: Botes | S7: Apie | V7: Sui Fon | X7: Barnes | AA7: Papou | AB7: Cecily
A8: 46058 | B8: Thursday | C8: Johnstons | D8: Theron | E8: Du Plessis | H8: Le Roux | I8: Klientjie | J8: Bierman | Q8: Botes | S8: Apie | X8: Barnes | AA8: Papou | AB8: Cecily
A9: 46059 | B9: Friday | D9: Theron | E9: Du Plessis | F9: Apie | I9: Klientjie | J9: Bierman | Q9: Botes | V9: Sui Fon | X9: Barnes | AA9: Papou | AB9: Cecily | AC9: Botha | AD9: Scholtz
A10: 46060 | B10: Saturday | F10: Apie | I10: Klientjie | Q10: Botes- Invoice March | AA10: Papou
A11: 46061 | B11: Sunday | F11: Apie | I11: Klientjie | AA11: Papou
A12: 46062 | B12: Monday | C12: Johnstons | D12: Theron | E12: Du Plessis | F12: Apie | I12: Klientjie | J12: Bierman | Q12: Botes | T12: Papou | U12: Ras | V12: Sui Fon | X12: Barnes | Z12: Place | AC12: Botha | AE12: Cecily | AF12: Maria Burgum
A13: 46063 | B13: Tuesday | C13: Johnstons | D13: Theron | E13: Du Plessis | I13: Klientjie | J13: Bierman | Q13: Botes | S13: Apie | T13: Papou | U13: Ras | X13: Barnes | Z13: Place | AE13: Cecily | AF13: Maria Burgum | AG13: Roux
A14: 46064 | B14: Wednesday | C14: Johnstons | D14: Theron | E14: Du Plessis | G14: Richards | H14: Wessels | I14: Klientjie | J14: Bierman | Q14: Botes | S14: Apie | T14: Papou | U14: Ras | V14: Sui Fon | X14: Barnes | Z14: Place | AC14: Botha | AE14: Cecily | AF14: Maria Burgum | AG14: Roux
A15: 46065 | B15: Thursday | C15: Johnstons | D15: Theron | E15: Du Plessis | G15: Richards | H15: Le Roux | J15: Bierman | L15: Klientjie | Q15: Botes | S15: Apie | T15: Papou | U15: Ras | X15: Barnes | Z15: Place | AE15: Cecily
A16: 46066 | B16: Friday | C16: Johnstons | D16: Theron | E16: Du Plessis | F16: Apie | G16: Richards | H16: Webb | J16: Bierman | L16: Klientjie | Q16: Botes | T16: Papou | U16: Ras | X16: Barnes | Z16: Place | AC16: Botha | AE16: Cecily | AG16: Roux
A17: 46067 | B17: Saturday | E17: Du Plessis | F17: Apie | L17: Klientjie | T17: Papou | U17: Ras
A18: 46068 | B18: Sunday | E18: Du Plessis | F18: Apie | L18: Klientjie | T18: Papou | U18: Ras
A19: 46069 | B19: Monday | C19: Johnstons | D19: Theron | E19: Du Plessis | F19: Apie | G19: Richards | J19: Bierman | L19: Klientjie | O19: Maria Burgum | Q19: Botes | X19: Barnes | Z19: Place | AA19: Papou | AC19: Botha | AE19: Cecily | AG19: Roux
A20: 46070 | B20: Tuesday | C20: Johnstons | D20: Theron | E20: Du Plessis | G20: Richards | J20: Bierman | L20: Klientjie | Q20: Botes | S20: Apie | U20: Oosthuizen | X20: Barnes | Z20: Place | AA20: Papou | AE20: Cecily | AG20: Roux
A21: 46071 | B21: Wednesday | C21: Johnstons | E21: Du Plessis | G21: Richards | H21: Wessels | J21: Bierman | K21: Theron | L21: Klientjie | O21: Maria Burgum | Q21: Botes | S21: Apie | U21: Oosthuizen | X21: Barnes | Z21: Place | AA21: Papou | AC21: Botha | AE21: Cecily | AG21: Roux
A22: 46072 | B22: Thursday | C22: Johnstons | E22: Du Plessis | G22: Richards | H22: Le Roux | I22: Klientjie | J22: Bierman | K22: Theron | M22: O Niell | Q22: Botes | S22: Apie | U22: Oosthuizen | X22: Barnes | AA22: Papou
A23: 46073 | B23: Friday | C23: Johnstons | E23: Du Plessis | F23: Apie | G23: Richards | H23: Webb | I23: Klientjie | J23: Bierman | K23: Theron | O23: Maria Burgum | Q23: Botes | U23: Oosthuizen | X23: Barnes | AA23: Papou | AC23: Botha | AG23: Roux | AH23: Scholtz
A24: 46074 | B24: Saturday | F24: Apie | G24: Richards | I24: Klientjie | K24: Theron | AA24: Papou
A25: 46075 | B25: Sunday | F25: Apie | G25: Richards | I25: Klientjie | K25: Theron | AA25: Papou
A26: 46076 | B26: Monday | C26: Johnstons | E26: Du Plessis | F26: Apie | G26: Richards | I26: Klientjie | J26: Bierman | K26: Theron | M26: De Waal | O26: Maria Burgum | Q26: Botes | T26: Papou | U26: Ras | X26: Barnes | Z26: Place | AB26: Oosthuizen | AG26: Roux
A27: 46077 | B27: Tuesday | C27: Johnstons | E27: Du Plessis | G27: Richards | I27: Klientjie | J27: Bierman | K27: Theron | M27: De Waal | Q27: Botes | S27: Apie | T27: Papou | U27: Ras | X27: Barnes | Z27: Place | AB27: Oosthuizen | AG27: Roux | AH27: Scholtz
A28: 46078 | B28: Wednesday | C28: Johnstons | D28: Theron | E28: Du Plessis | G28: Richards | H28: Wessels | I28: Klientjie | J28: Bierman | M28: De Waal | O28: Maria Burgum | Q28: Botes | S28: Apie | T28: Papou | U28: Ras | X28: Barnes | Z28: Place | AB28: Oosthuizen | AG28: Roux
A29: 46079 | B29: Thursday | C29: Johnstons | D29: Theron | E29: Du Plessis | F29: Apie | G29: Richards | H29: Le Roux | I29: Klientjie | J29: Bierman | M29: De Waal | O29: Maria Burgum | Q29: Botes | T29: Papou | U29: Ras | X29: Barnes | Z29: Place | AB29: Oosthuizen | AC29: Scroope | AH29: Scholtz
A30: 46080 | B30: Friday | C30: Johnstons | D30: Theron | E30: Du Plessis | F30: Apie | G30: Richards | H30: Webb | I30: Klientjie | J30: Bierman | M30: De Waal | O30: Maria Burgum | Q30: Botes | T30: Papou | U30: Ras | X30: Barnes | AB30: Oosthuizen | AC30: Scroope | AG30: Roux
A31: 46081 | B31: Saturday | D31: Theron | F31: Apie | G31: Richards | I31: Klientjie | M31: De Waal | T31: Papou | U31: Ras | AC31: Scroope
A35: Days Worked | C35: 19 | D35: 16 | F35: 16 | G35: 17 | H35: 11 | I35: 20 | J35: 20 | K35: 7 | L35: 7 | M35: 7 | O35: 8 | Q35: 21 | S35: 12 | T35: 14 | U35: 18 | V35: 5 | X35: 20 | Z35: 12 | AA35: 14 | AB35: 10 | AC35: 10 | AD35: 1 | AE35: 8 | AF35: 3 | AG35: 11 | AH35: 3
A36: Money added | D36: 250 | L36: 3500
A37: Money Borrowed | G37: 500 | M37: 450 | O37: 450 | Q37: 1000 | S37: 2500 | T37: 450 | U37: 500 | V37: 450 | AB37: 1000 | AC37: 150 | AF37: 450
A38: Total Amount | B38: =SUM(C38:AJ38) | C38: =C2*C35 | D38: =D2*D35+D36 | E38: 8900 | F38: =F35*F2-F37 | G38: =G35*G2-G37 | H38: =H2*H35 | I38: =I2*I35 | J38: =J2*J35+J36 | K38: =K2*K35 | L38: =L2*L35+L36 | M38: =M2*M35-M37 | N38: =N2*N35 | O38: =O2*O35-O37 | P38: =P2*P35-P37 | Q38: =Q2*Q35-Q37 | R38: =R2*R35 | S38: =S2*S35-S37 | T38: =T2*T35-T37 | U38: =SUM(U2*U35-U37) | V38: =V2*V35-V37 | X38: =X2*X35 | Z38: =Z2*Z35 | AA38: =AA2*AA35 | AB38: =AB2*AB35-AB37 | AC38: =AC2*AC35-AC37 | AD38: =AD2*AD35 | AE38: =AE2*AE35 | AF38: =AF2*AF35-AF37 | AG38: =AG2*AG35 | AH38: =AH2*AH35

Sheet Client Mar 2026
A1: Johnstons- monthly | E1: Van Der Linde- monthly | I1: John Bierman- monthly | M1: Scroope | Q1: Trevor Botes- monthly | U1: Dirk Le Roux- monthly
A2: Income | E2: Income | I2: Income | M2: Income | Q2: Income | U2: Income
A3: Date: | C3: Payment | E3: Date: | G3: Payment | I3: Date: | K3: Payment | M3: Date: | O3: Payment | Q3: Date: | S3: Payment | U3: Date: | W3: Payment
A4: 46082 | B4: Invoiced NPC | C4: 24800 | E4: 46082 | F4: Invoiced NPC | G4: 22200 | I4: 46082 | J4: Invoiced TCH | K4: 17000 | Q4: 46082 | R4: invoiced | S4: 17250 | U4: 46082 | V4: invoiced TCH | W4: 3000
C8: =SUM(C4:C7) | G8: =SUM(G4:G7) | K8: =SUM(K4:K7) | O8: =SUM(O4:O7) | S8: =SUM(S4:S7) | W8: =SUM(W4:W7)
A9: Expenses | E9: Expenses | I9: Expenses | M9: Expenses | Q9: Expenses | U9: Expenses
A10: Date: | B10: Expense Name | C10: Amount | E10: Date: | F10: Expense Name | G10: Amount | I10: Date: | J10: Expense Name | K10: Amount | M10: Date: | N10: Expense Name | O10: Amount | Q10: Date: | R10: Expense Name | S10: Amount | U10: Date: | V10: Expense Name | W10: Amount
A11: 46082 | B11: Linda | E11: 46082 | F11: Emily | I11: 46082 | J11: Susan | N11: Merriam | Q11: 46082 | R11: Siphilisiwe (Patrica) | U11: 46082 | V11: Ruth
E12: 46082 | F12: Emma
E13: 46082 | F13: Uber
A23: Total Expense | C23: =SUM(C11:C22) | E23: Total Expense | G23: =SUM(G11:G22) | I23: Total Expense | K23: =SUM(K11:K22) | M23: Total Expense | O23: =SUM(O11:O14) | Q23: Total Expense | S23: =SUM(S11:S22) | U23: Total Expense
A24: Income - Expense | C24: =MIN(C4-C23) | E24: Income - Expense | G24: =MIN(G4-G23) | I24: Income - Expense | K24: =MIN(K4-K23) | M24: Income - Expense | O24: =MIN(O8-O23) | Q24: Income - Expense | S24: =MIN(S4-S23) | U24: Income - Expense
A26: Angela/ Dimitri Paoadopoulos- weekly | E26: Du Plessis | I26: Mia Ras- monthly | M26: Megan Barnes | Q26: Johanna Van Heerden- monthly | U26: Derek Halls
A27: Income | E27: Income | I27: Income | M27: Income | Q27: Income | U27: Income
A28: Date: | C28: Payment | E28: Date: | G28: Payment | I28: Date: | K28: Payment | M28: Date: | O28: Payment | Q28: Date: | S28: Payment | U28: Date: | W28: Payment
A29: 46085 | B29: Invoiced | C29: 6650 | E29: 46082 | F29: invoiced | G29: 12500 | I29: 46082 | J29: invoiced | K29: 11900 | M29: 46082 | N29: invoiced | O29: 13000 | Q29: 46082 | R29: Invoiced TCH | S29: 23250 | U29: 46082 | V29: invoiced | W29: 11600
A30: 46092 | B30: Invoiced | C30: 6650
A31: 46097 | B31: Invoiced | C31: 6650
A32: 46106 | B32: Invoiced | C32: 6650
A33: 46112
C34: =SUM(C29:C33) | G34: =SUM(G29:G32) | K34: =SUM(K29:K33) | O34: =SUM(O29:O32) | S34: =SUM(S29:S32) | W34: =SUM(W29:W32)
A35: Expenses | E35: Expenses | I35: Expenses | M35: Expenses | Q35: Expenses | U35: Expenses
A36: Date: | B36: Expense Name | C36: Amount | E36: Date: | F36: Expense Name | G36: Amount | I36: Date: | J36: Expense Name | K36: Amount | M36: Date: | N36: Expense Name | O36: Amount | Q36: Date: | R36: Expense Name | S36: Amount | U36: Date: | V36: Expense Name | W36: Amount
A37: 46082 | B37: Tracy | E37: 46082 | I37: 46082 | J37: Marion | M37: 46082 | N37: Leah | Q37: 46082 | R37: Christina | U37: 46082 | V37: Annika
B38: Musa | F38: Joyce | Q38: 46082 | R38: Ada
A48: Total Expense | E48: Total Expense | I48: Total Expense | M48: Total Expense | Q48: Total Expense | U48: Total Expense
A49: Income - Expense | E49: Income - Expense | I49: Income - Expense | M49: Income - Expense | Q49: Income - Expense | U49: Income - Expense
A51: Roux- Esme | E51: Carolina Richards | I51: Webb- Sonja | M51: Andre Theron- monthly | Q51: De Waal- weekly | U51: Morrison
A52: Income | E52: Income | I52: Income | M52: Income | Q52: Income | U52: Income
A53: Date: | C53: Payment | E53: Date: | G53: Payment | I53: Date: | K53: Payment | M53: Date: | O53: Payment | Q53: Date: | S53: Payment | U53: Date: | W53: Payment
A54: 46082 | B54: invoiced | C54: 5250 | E54: 46082 | F54: invoiced | G54: 23250 | I54: 46082 | J54: invoiced | K54: 3000 | M54: 46082 | N54: invoiced | O54: 24000 | Q54: 46082 | R54: invoiced | S54: 6650
Q55: 46087 | R55: invoiced | S55: 6650
Q56: 13 | R56: invoiced | S56: 6650
Q57: 46101 | R57: invoiced | S57: 6650
Q58: 46108 | R58: invoiced | S58: 6650
C59: =SUM(C54:C58) | G59: =SUM(G54:G58) | K59: =SUM(K54:K58) | O59: =SUM(O54:O57) | S59: =SUM(S54:S58) | W59: =SUM(W54:W57)
A60: Expenses | E60: Expenses | I60: Expenses | M60: Expenses | Q60: Expenses | U60: Expenses
A61: Date: | B61: Expense Name | C61: Amount | E61: Date: | F61: Expense Name | G61: Amount | I61: Date: | J61: Expense Name | K61: Amount | M61: Date: | N61: Expense Name | O61: Amount | Q61: Date: | R61: Expense Name | S61: Amount | U61: Date: | V61: Expense Name | W61: Amount
B62: Julia | F62: Julia | J62: Ruth | M62: 46054 | N62: Sophia | R62: Merriam | U62: 46054
N63: Ndai
A74: Total Expense | E74: Total Expense | I74: Total Expense | M74: Total Expense | Q74: Total Expense | U74: Total Expense
A75: Income - Expense | E75: Income - Expense | I75: Income - Expense | M75: Income - Expense | Q75: Income - Expense | U75: Income - Expense
A77: Kotie- Rental | E77: Scholtz | I77: Maria Burgum- Weekly | M77: Jean Place | Q77: Oosthuizen- Weekly | U77: O'Neill
A78: Income | E78: Income | I78: Income | M78: Income | Q78: Income | U78: Income
A79: Date: | C79: Payment | E79: Date: | G79: Payment | I79: Date: | K79: Payment | M79: Date: | O79: Payment | Q79: Date: | S79: Payment | U79: Date: | W79: Payment
A80: 46082 | B80: invoiced | C80: 600 | E80: 46082 | F80: invoiced | G80: 6750 | I80: 46082 | J80: invoiced | K80: 2250 | U80: 46083 | V80: invoiced | W80: 8250
I81: 46087 | J81: invoiced | K81: 2250 | U81: 46090 | V81: invoiced | W81: 19550 | X81: Day shift till month end
I82: 46097 | J82: invoiced | K82: 2250 | U82: 46097 | V82: invoiced | W82: 18700
C85: =SUM(C80:C84) | G85: =SUM(G80:G84) | K85: =SUM(K80:K84) | O85: =SUM(O80:O84) | S85: =SUM(S80:S84) | W85: =SUM(W80:W84)
A86: Expenses | E86: Expenses | I86: Expenses | M86: Expenses | Q86: Expenses | U86: Expenses
A87: Date: | B87: Expense Name | C87: Amount | E87: Date: | F87: Expense Name | G87: Amount | I87: Date: | J87: Expense Name | K87: Amount | M87: Date: | N87: Expense Name | O87: Amount | Q87: Date: | R87: Expense Name | S87: Amount | U87: Date: | V87: Expense Name | W87: Amount
F88: Martha Mashishi | J88: Martha Sone | N88: Nipho
F89: Mbali | J89: Syliva
A100: Total Expense | E100: Total Expense | I100: Total Expense | M100: Total Expense | Q100: Total Expense | U100: Total Expense
A101: Income - Expense | E101: Income - Expense | I101: Income - Expense | M101: Income - Expense | Q101: Income - Expense | U101: Income - Expense
A103: Fisher | E103: Alberts | I103: Peens | M103: Ingham | Q103: Gildenhyus
A104: Income | E104: Income | I104: Income | M104: Income | Q104: Income
A105: Date: | C105: Payment | E105: Date: | G105: Payment | I105: Date: | K105: Payment | M105: Date: | O105: Payment | Q105: Date: | S105: Payment
A106: 46082 | B106: invoiced | C106: 5500 | E106: 46082 | F106: invoiced | G106: 2850 | I106: 46088 | J106: Invioiced | K106: 10500 | M106: 46096 | N106: Invioiced | O106: 950 | Q106: 46107 | R106: invoiced | S106: 1750
E107: 46085 | F107: invoiced | G107: 950 | I107: 46097 | J107: Invioiced | K107: 6000 | M107: 46097 | N107: Invioiced | O107: 1750 | Q107: 46108 | R107: invoiced | S107: 3800
M108: 46098 | N108: Invioiced | O108: 1750
M109: 46100 | N109: Invioiced | O109: 1750
C111: =SUM(C106:C110) | G111: =SUM(G106:G110) | K111: =SUM(K106:K110) | O111: =SUM(O106:O110) | S111: =SUM(S106:S110)
A112: Expenses | E112: Expenses | I112: Expenses | M112: Expenses | Q112: Expenses
A113: Date: | B113: Expense Name | C113: Amount | E113: Date: | F113: Expense Name | G113: Amount | I113: Date: | J113: Expense Name | K113: Amount | M113: Date: | N113: Expense Name | O113: Amount | Q113: Date: | R113: Expense Name | S113: Amount
R114: Emily
A126: Total Expense | E126: Total Expense | I126: Total Expense | M126: Total Expense | Q126: Total Expense
A127: Income - Expense | E127: Income - Expense | I127: Income - Expense | M127: Income - Expense | Q127: Income - Expense
A132: Total from Clients | B132: =SUM(C8+G8+K8+O8+S8+W8+C34+G34+K34+O34+S34+W34+C59+G59+K59+O59+S59+W59+C85+G85+K85+O85+S85+W85+C111+G111+K111+O111+S111)

Sheet Sheet1

Sheet Caregiver Mar 2026
C1: Linda Rapuluchukwa | D1: Sophie Koga | E1: Joyce Mutambiranwa | F1: Emily Mentula | G1: Cynthia Makondo | H1: Ruth Nnadi | I1: Christina Maluleka | J1: Susan Murire | K1: Ndai Mapenyenye | L1: Adaobi Ejikeme | M1: Merriam Maluleke | N1: Jane Mokgaetsi Moekwa | O1: Sylvia Nene | P1: Matodzi Sylvia Mutavhatsindi | Q1: Siphilisiwe Nkala(Patricia) | R1: Refiloe Khuzwayo | S1: Mmamaswabi Emma Dhlamini | T1: Tracy Nothando Nyirenda | U1: Marion Goeda | V1: Siphethokhuhle Nkomo | W1: Matshidiso Leah Aphane | X1: Monique Bosch | Y1: Nhlakanipho (Nipho) Tshabalala | Z1: Musa Zulu | AA1: Busisiwe Mandiyanike | AB1: Emiia Mshaba | AC1: Martha Mashishi | AD1: Sara Mdaka | AE1: Martha Sona | AF1: Julia Ramoroka | AG1: Mbali Ndaba | AH1: Philadelphia Mashaba | AI1: Annika Van Rensburg | AJ1: Fortunate Mabizela | AK1: Beauty Masopye | AL1: Thalitha Managa | AM1: Dolly Chauke | AN1: Annie Mabuto
B2: Caregiver Price | D2: 550 | E2: 500 | F2: 450 | G2: 450 | H2: 450 | I2: 450 | J2: 450 | K2: 500 | L2: 450 | M2: 450 | N2: 450 | O2: 450 | P2: 450 | Q2: 450 | R2: 450 | S2: 450 | T2: 450 | U2: 450 | V2: 450 | Y2: 500 | Z2: 450 | AA2: 450 | AB2: 450 | AC2: 450 | AD2: 500 | AE2: 450 | AF2: 450 | AG2: 450 | AH2: 500 | AJ2: 450 | AK2: 450 | AL2: 500 | AM2: 500 | AN2: 450
A3: Date | B3: Days of Week
A4: 46081 | B4: Saturday | L4: O Niel -R500 | AH4: O Niel
A5: 46082 | B5: Sunday | D5: Theron | F5: Apie | G5: Richards | I5: Klientjie | L5: O Niel -R500 | M5: De Waal | T5: Papou | AB5: Scroope- R400 | AH5: O Niel
A6: 46083 | B6: Monday | C6: Johnstons | D6: Theron | E6: Du Plessis | F6: Apie | G6: Richards | I6: Klientjie | J6: Bierman | M6: De Waal | O6: Maria Burgum | Q6: Botes | U6: Alberts | W6: Barnes | Y6: O Niel | Z6: Papou | AB6: Alberts | AG6: Scholtz | AH6: O Niel | AI6: Cecily
A7: 46084 | B7: Tuesday | C7: Johnstons | D7: Theron | E7: Du Plessis | G7: Richards | I7: Klientjie | J7: Bierman | M7: De Waal | Q7: Botes | S7: Apie | U7: Alberts | W7: Barnes | Y7: O Niel | Z7: Papou | AH7: O Niel | AI7: Cecily
A8: 46085 | B8: Wednesday | C8: Johnstons | E8: Du Plessis | G8: Richards | I8: Klientjie | J8: Bierman | K8: Theron | M8: De Waal | O8: Maria Burgum | Q8: Botes | S8: Apie | W8: Barnes | Y8: O Niel | Z8: Papou | AB8: Alberts | AH8: O Niel | AI8: Cecily
A9: 46086 | B9: Thursday | C9: Johnstons | E9: Du Plessis | G9: Richards | H9: Le Roux | I9: Klientjie | J9: Bierman | K9: Theron | M9: De Waal | Q9: Botes | S9: Apie | W9: Barnes | Y9: O Niel | AG9: Scholtz | AH9: O Niel | AI9: Cecily | AJ9: Papou
A10: 46087 | B10: Friday | C10: Johnstons | E10: Du Plessis | G10: Richards | H10: Webb | I10: Klientjie | J10: Bierman | K10: Theron | M10: De Waal | O10: Maria Burgum | Q10: Botes | S10: Apie | V10: Richards | W10: Barnes | Y10: O Niel | AH10: O Niel | AI10: Cecily | AJ10: Papou
A11: 46088 | B11: Saturday | I11: Klientjie | K11: Theron | L11: O Niel -R500 | M11: De Waal | S11: Apie | V11: Richards | AG11: O Niel -R500 | AJ11: Papou
A12: 46089 | B12: Sunday | H12: Carli - R500 | I12: Klientjie | K12: Theron | L12: O Niel -R500 | M12: De Waal | S12: Apie | V12: Richards | AB12: Carli - R500 | AG12: O Niel -R500 | AJ12: Papou
A13: 46090 | B13: Monday | C13: Johnstons | E13: Du Plessis | F13: Apie | H13: Carli - R500 | I13: Klientjie | J13: Bierman | K13: Theron | M13: De Waal | O13: Maria Burgum | Q13: Botes | U13: Ras | V13: Richards | W13: Barnes | Y13: O Niel | AB13: Carli - R500 | AD13: O Niel | AG13: Scholtz | AI13: Cecily | AJ13: Papou
A14: 46091 | B14: Tuesday | C14: Johnstons | E14: Du Plessis | F14: Apie | H14: Carli - R1000 | I14: Klientjie | J14: Bierman | K14: Theron | Q14: Botes | U14: Ras | V14: Richards | W14: Barnes | Y14: O Niel | Z14: Papou | AD14: O Niel | AI14: Cecily | AK14: De Waal
A15: 46092 | B15: Wednesday | C15: Johnstons | E15: Du Plessis | F15: Apie | H15: Carli - R500 | I15: Klientjie | J15: Bierman | O15: Maria Burgum | Q15: Botes | U15: Ras | W15: Barnes | Y15: O Niel | Z15: Papou | AD15: O Niel | AF15: Theron | AI15: Cecily | AK15: De Waal | AL15: Carli - R500
A16: 46093 | B16: Thursday | C16: Johnstons | E16: Du Plessis | F16: Apie | H16: Le Roux | J16: Bierman | L16: Klientjie | Q16: Botes | U16: Ras | W16: Barnes | Y16: O Niel | Z16: Papou | AD16: O Niel | AF16: Theron | AG16: Scholtz/ Carli | AK16: De Waal | AL16: Carli - R500
A17: 46094 | B17: Friday | C17: Johnstons | E17: Du Plessis | F17: Apie | H17: Webb | J17: Bierman | L17: Klientjie | O17: Maria Burgum | Q17: Botes | U17: Ras | W17: Barnes | Y17: O Niel | Z17: Papou | AB17: O Niel | AF17: Theron | AG17: Carli - R500 | AI17: Cecily | AK17: De Waal | AL17: Carli - R500
A18: 46095 | B18: Saturday | F18: Apie | G18: Richards | L18: Klientjie | U18: Ras | Z18: Papou | AB18: O Niel | AF18: Theron | AG18: Carli - R500 | AK18: De Waal | AL18: Carli - R500 | AM18: O Niel
A19: 46096 | B19: Sunday | F19: Apie | G19: Richards | H19: Carli - R500 | L19: Klientjie | M19: Ingham | U19: Ras | Y19: O Niel | Z19: Papou | AB19: O Niel | AF19: Theron | AK19: De Waal | AL19: Carli - R500
A20: 46097 | B20: Monday | C20: Johnstons | E20: Du Plessis | G20: Richards | H20: Carli - R500 | I20: Klientjie | J20: Bierman | O20: Maria Burgum | Q20: Botes | S20: Apie | V20: Ingham | W20: Barnes | AB20: O Niel | AF20: Theron | AG20: Scholtz | AI20: Cecily | AJ20: Papou | AK20: De Waal | AM20: O Niel
A21: 46098 | B21: Tuesday | C21: Johnstons | E21: Du Plessis | G21: Richards | I21: Klientjie | J21: Bierman | M21: De Waal | Q21: Botes | S21: Apie | U21: Ingham | V21: Ingham | W21: Barnes | AB21: O Niel | AF21: Theron | AI21: Cecily | AJ21: Papou | AM21: O Niel
A22: 46099 | B22: Wednesday | C22: Johnstons | E22: Du Plessis | G22: Richards | I22: Klientjie | J22: Bierman | K22: Theron | M22: De Waal | O22: Maria Burgum | Q22: Botes | S22: Apie | U22: Ingham | V22: Ingham | W22: Barnes | AB22: O Niel | AI22: Cecily | AJ22: Papou | AM22: O Niel
A23: 46100 | B23: Thursday | C23: Johnstons | E23: Du Plessis | F23: Apie | G23: Richards | H23: Le Roux | I23: Klientjie | J23: Bierman | K23: Theron | M23: De Waal | Q23: Botes | U23: Ingham | V23: Ingham | W23: Barnes | AB23: O Niel | AG23: Scholtz | AI23: Cecily | AJ23: Papou | AM23: O Niel
A24: 46101 | B24: Friday | C24: Johnstons | E24: Du Plessis | F24: Apie | G24: Richards | H24: Webb | I24: Klientjie | J24: Bierman | K24: Theron | M24: De Waal | O24: Maria Burgum | Q24: Botes | U24: Ingham | W24: Barnes | Z24: Papou | AB24: O Niel | AI24: Cecily | AM24: O Niel
A25: 46102 | B25: Saturday | F25: Apie | G25: Richards | I25: Klientjie | K25: Theron | M25: De Waal | Y25: O Niel | Z25: Papou | AB25: O Niel
A26: 46103 | B26: Sunday | F26: Apie | G26: Richards | I26: Klientjie | K26: Theron | M26: De Waal | Y26: O Niel | Z26: Papou | AB26: O Niel
A27: 46104 | B27: Monday | C27: Johnstons | E27: Du Plessis | F27: Apie | I27: Klientjie | J27: Bierman | K27: Theron | M27: De Waal | O27: Maria Burgum | Q27: Botes | U27: Ras | W27: Barnes | Y27: O Niel | Z27: Papou | AB27: O Niel | AG27: Scholtz | AI27: Cecily | AN27: Richards
A28: 46105 | B28: Tuesday | C28: Johnstons | E28: Du Plessis | F28: Apie | I28: Klientjie | J28: Bierman | K28: Theron | M28: De Waal | Q28: Botes | U28: Ras | W28: Barnes | Y28: O Niel | Z28: Papou | AB28: O Niel | AI28: Cecily | AN28: Richards
A29: 46106 | B29: Wednesday | C29: Johnstons | E29: Du Plessis | I29: Klientjie | J29: Bierman | K29: Theron | M29: De Waal | O29: Maria Burgum | Q29: Botes | S29: Apie | U29: Ras | W29: Barnes | Y29: O Niel | AB29: O Niel | AI29: Cecily | AJ29: Papou | AN29: Richards
A30: 46107 | B30: Thursday | C30: Johnstons | E30: Du Plessis | F30: Anne Marie | H30: Le Roux | I30: Klientjie | J30: Bierman | K30: Theron | M30: De Waal | Q30: Botes | S30: Apie/ Anne- Marie | U30: Ras | W30: Barnes | Y30: O Niel | AB30: O Niel | AG30: Scholtz | AI30: Cecily | AJ30: Papou | AN30: Richards
A31: 46108 | B31: Friday | C31: Johnstons | E31: Du Plessis | H31: Webb | I31: Klientjie | J31: Bierman | O31: Maria Burgum | Q31: Botes | S31: Apie | U31: Ras | W31: Barnes | Y31: O Niel | AB31: O Niel | AI31: Cecily | AJ31: Papou | AK31: De Waal | AN31: Richards
A32: 46109 | B32: Saturday | F32: Anne Marie | I32: Klientjie | S32: Apie | U32: Ras | V32: O Niel | Y32: O Niel | AJ32: Papou | AK32: De Waal | AN32: Richards
A33: 46110 | B33: Sunday | F33: Anne Marie | I33: Klientjie | S33: Apie | U33: Ras | V33: O Niel | Y33: O Niel | AJ33: Papou | AK33: De Waal | AN33: Richards
A34: 46111 | B34: Monday | C34: Johnstons | E34: Du Plessis | F34: Anne Marie | G34: Richards | I34: Klientjie | J34: Bierman | O34: Maria Burgum | Q34: Botes | S34: Apie | V34: O Niel | W34: Barnes | Z34: Papou | AB34: O Niel | AG34: Scholtz | AI34: Cecily | AK34: De Waal
A35: 46112 | B35: Tuesday | C35: Johnstons | E35: Du Plessis | F35: Apie/ Anne- Marie | G35: Richards | I35: Klientjie | J35: Bierman | Q35: Botes | V35: O Niel | W35: Barnes | Z35: Papou | AB35: O Niel | AI35: Cecily | AK35: De Waal
A36: Days Worked | C36: 22 | D36: 3 | E36: 22 | F36: 21 | G36: 17 | H36: 15 | I36: 27 | J36: 22 | K36: 16 | L36: 8 | M36: 20 | O36: 13 | Q36: 22 | S36: 16 | T36: 1 | U36: 20 | V36: 13 | W36: 22 | Y36: 20 | Z36: 16 | AB36: 22 | AD36: 4 | AF36: 7 | AG36: 14 | AH36: 7 | AJ36: 14 | AK36: 12 | AL36: 5 | AM36: 6 | AN36: 7
A37: Money added | H37: 350 | L37: 3700 | V37: 200 | AB37: 950 | AG37: 250 | AI37: 9600
A38: Money Borrowed | M38: 1000 | Q38: 450 | S38: 150 | W38: 450 | Z38: 500 | AB38: 1000 | AD38: 500 | AF38: 500 | AG38: 750 | AH38: 500 | AI38: 430 | AJ38: 500 | AK38: 500 | AL38: 500 | AN38: 500
A39: Total Amount | B39: =SUM(C39:AN39) | C39: 10500 | D39: =D2*D36+D37 | E39: 8000 | F39: =F36*F2-F38 | G39: =G36*G2-G38 | H39: =H2*H36+H37 | I39: =I2*I36 | J39: =J2*J36+J37 | K39: =K2*K36 | L39: =L2*L36+L37 | M39: =M2*M36-M38 | N39: =N2*N36 | O39: =O2*O36-O38 | P39: =P2*P36-P38 | Q39: =Q2*Q36-Q38 | R39: =R2*R36 | S39: =S2*S36-S38 | T39: =T2*T36-T38 | U39: =SUM(U2*U36-U38) | V39: =V2*V36-V38+V37 | W39: 6650 | Y39: =Y2*Y36 | Z39: =Z2*Z36-Z38 | AA39: =AA2*AA36-AA38 | AB39: =AB2*AB36-AB38+AB37 | AC39: =AC2*AC36 | AD39: =AD2*AD36-AD38 | AE39: =AE2*AE36-AE38 | AF39: =AF2*AF36-AF38 | AG39: =AG2*AG36+AG37-AG38 | AH39: =AH2*AH36-AH38 | AI39: =AI37-AI38 | AJ39: =AJ2*AJ36-AJ38 | AK39: =AK2*AK36-AK38 | AL39: =AL2*AL36-AL38 | AM39: =AM2*AM36 | AN39: =AN2*AN36-AN38

Sheet Client Apr 2026
A1: Johnstons- monthly | E1: John Bierman- monthly | I1: Trevor Botes- monthly | M1: Dirk Le Roux- monthly | Q1: Mia Ras- monthly
A2: Income | E2: Income | I2: Income | M2: Income | Q2: Income
A3: Date: | C3: Payment | E3: Date: | G3: Payment | I3: Date: | K3: Payment | M3: Date: | O3: Payment | Q3: Date: | S3: Payment
A4: 46113 | B4: Invoiced NPC | C4: 16500 | E4: 46113 | F4: Invoiced TCH | G4: 17600 | I4: 46113 | J4: invoiced | K4: 16500 | M4: 46113 | N4: invoiced TCH | O4: 3750 | Q4: 46113 | R4: invoiced | S4: 11900
C8: =SUM(C4:C7) | G8: =SUM(G4:G7) | K8: =SUM(K4:K7) | O8: =SUM(O4:O7) | S8: =SUM(S4:S7)
A9: Expenses | E9: Expenses | I9: Expenses | M9: Expenses | Q9: Expenses
A10: Date: | B10: Expense Name | C10: Amount | E10: Date: | F10: Expense Name | G10: Amount | I10: Date: | J10: Expense Name | K10: Amount | M10: Date: | N10: Expense Name | O10: Amount | Q10: Date: | R10: Expense Name | S10: Amount
A11: 46113 | B11: Linda | E11: 46113 | F11: Susan | I11: 46113 | J11: Siphilisiwe (Patrica) | M11: 46113 | N11: Ruth | Q11: 46113 | R11: Marion
A23: Total Expense | C23: =SUM(C11:C22) | E23: Total Expense | G23: =SUM(G11:G22) | I23: Total Expense | K23: =SUM(K11:K22) | M23: Total Expense | Q23: Total Expense
A24: Income - Expense | C24: =MIN(C4-C23) | E24: Income - Expense | G24: =MIN(G4-G23) | I24: Income - Expense | K24: =MIN(K4-K23) | M24: Income - Expense | Q24: Income - Expense
A26: Megan Barnes | E26: Johanna Van Heerden- monthly | I26: Derek Halls | M26: Carolina Richards | Q26: Webb- Sonja
A27: Income | E27: Income | I27: Income | M27: Income | Q27: Income
A28: Date: | C28: Payment | E28: Date: | G28: Payment | I28: Date: | K28: Payment | M28: Date: | O28: Payment | Q28: Date: | S28: Payment
A29: 46113 | B29: invoiced | C29: 13000 | E29: 46113 | F29: Invoiced TCH | G29: 23250 | I29: 46113 | J29: invoiced | K29: 17200 | M29: 46113 | N29: invoiced | O29: 24000 | Q29: 46113 | R29: invoiced | S29: 3000
C34: =SUM(C29:C32) | G34: =SUM(G29:G32) | K34: =SUM(K29:K32) | O34: =SUM(O29:O33) | S34: =SUM(S29:S33)
A35: Expenses | E35: Expenses | I35: Expenses | M35: Expenses | Q35: Expenses
A36: Date: | B36: Expense Name | C36: Amount | E36: Date: | F36: Expense Name | G36: Amount | I36: Date: | J36: Expense Name | K36: Amount | M36: Date: | N36: Expense Name | O36: Amount | Q36: Date: | R36: Expense Name | S36: Amount
A37: 46082 | B37: Leah | E37: 46082 | F37: Christina | I37: 46113 | J37: Annika | N37: Cynthia | R37: Ruth
E38: 46082 | F38: Ada | N38: Annie
A48: Total Expense | E48: Total Expense | I48: Total Expense | M48: Total Expense | Q48: Total Expense
A49: Income - Expense | E49: Income - Expense | I49: Income - Expense | M49: Income - Expense | Q49: Income - Expense
A51: De Waal- weekly | E51: O'Neill | I51: Scroope | M51: Fisher | Q51: Anton Steyn/ Emce
A52: Income | E52: Income | I52: Income | M52: Income | Q52: Income
A53: Date: | C53: Payment | E53: Date: | G53: Payment | I53: Date: | K53: Payment | M53: Date: | O53: Payment | Q53: Date: | S53: Payment
A54: 46113 | B54: Invoiced | C54: 24700 | E54: 46113 | F54: invoiced | G54: 45000 | I54: 46113 | J54: Invoiced | K54: 3350 | M54: 46113 | N54: invoiced | O54: 5500 | Q54: 46113 | R54: invoiced | S54: 3800
C59: =SUM(C54:C58) | G59: =SUM(G54:G58) | K59: =SUM(K54:K58) | O59: =SUM(O54:O58) | S59: =SUM(S54:S58)
A60: Expenses | E60: Expenses | I60: Expenses | M60: Expenses | Q60: Expenses
A61: Date: | B61: Expense Name | C61: Amount | E61: Date: | F61: Expense Name | G61: Amount | I61: Date: | J61: Expense Name | K61: Amount | M61: Date: | N61: Expense Name | O61: Amount | Q61: Date: | R61: Expense Name | S61: Amount
B62: Merriam | F62: Nipho | R62: Emily
B63: Beauty | F63: Emilia
F64: Siphe
A73: Total Expense | E73: Total Expense | I73: Total Expense | K73: =SUM(K61:K64) | M73: Total Expense | Q73: Total Expense
A74: Income - Expense | E74: Income - Expense | I74: Income - Expense | K74: =MIN(K58-K73) | M74: Income - Expense | Q74: Income - Expense
A76: Angela/ Dimitri Paoadopoulos | E76: Maria Burgum
A77: Income | E77: Income
A78: Date: | C78: Payment | E78: Date: | G78: Payment
A79: 46113 | B79: Invoiced | C79: 6650 | E79: 46113 | F79: invoiced | G79: 2250
A80: 46118
A81: 13
A82: 46132
A83: 46139
C84: =SUM(C79:C83) | G84: =SUM(G79:G83)
A85: Expenses | E85: Expenses
A86: Date: | B86: Expense Name | C86: Amount | E86: Date: | F86: Expense Name | G86: Amount
A87: 46082 | B87: Fortunate | F87: Syliva
B88: Musa
A98: Total Expense | E98: Total Expense
A99: Income - Expense | E99: Income - Expense
A105: Total from Clients | B105: =SUM(C8+G8+K8+O8+S8+C34+G34+G34+K34+O34+S34+C59+G59+K59+C84+G84+O59+S59)

Sheet Caregiver Apr 2026
